Workbook

Sheet Master
A1: publication_id | B1: year | C1: date | D1: title | E1: authors | F1: pang_faculty_authors | G1: document_type | H1: source_title | I1: tertiary_title | J1: publisher | K1: place_published | L1: volume | M1: issue | N1: pages | O1: doi | P1: doi_normalized | Q1: issn | R1: isbn | S1: url | T1: abstract | U1: language | V1: source | W1: legacy_nid | X1: legacy_status | Y1: include_in_master | Z1: data_quality_flags | AA1: scopus_eid | AB1: verification_status | AC1: verification_source_url
A2: scopus-10-1109-taes-2025-3619912 | B2: 2026 | D2: A Split Pulse Fusion Method for Radar Reconnaissance | E2: Ronghua Guo; Yang-Yang Dong; Dan Bao; Chunxi Dong; Sergio Vitale; Giampaolo Ferraioli; Vito Pascazio; Wenbo Li; Zhiyuan Li | F2: Giampaolo Ferraioli | G2: Journal Article | H2: IEEE Transactions on Aerospace and Electronic Systems | L2: 62 | N2: 217-233 | O2: 10.1109/TAES.2025.3619912 | P2: 10.1109/taes.2025.3619912 | S2: https://doi.org/10.1109/TAES.2025.3619912 | V2: scopus | Y2: yes | AB2: verified_scopus | AC2: https://www.sciencedirect.com/author/7003486376/vito-pascazio
A3: scopus-10-3390-automation7020036 | B3: 2026 | C3: 2026-02-25 | D3: Intelligent Tomato Leaf Disease Detection and Automated Spray Prescription Using YOLOv9: A Smart Agriculture Approach | E3: Shahab Ul Islam; Giampaolo Ferraioli; Ghassan Husnain; Abdul Waheed; Vito Pascazio | F3: Giampaolo Ferraioli | G3: Journal Article | H3: Automation | L3: 7 | M3: 2 | N3: 36 | O3: 10.3390/automation7020036 | P3: 10.3390/automation7020036 | S3: https://doi.org/10.3390/automation7020036 | V3: scopus | Y3: yes | AB3: verified_scopus | AC3: https://www.sciencedirect.com/author/7003486376/vito-pascazio
A4: scopus-10-1016-j-oceaneng-2025-123471 | B4: 2026 | C4: 2026-01-15 | D4: Sea state reconstruction based on the Spearman rank correlation using full-scale data from a containership | E4: Silvia Ascione; Ulrik D. Nielsen; Vincenzo Piscopo; Gaute Storhaug | F4: Vincenzo Piscopo | G4: Journal Article | H4: Ocean Engineering | L4: 343 | M4: Part 4 | N4: 123471 | O4: 10.1016/j.oceaneng.2025.123471 | P4: 10.1016/j.oceaneng.2025.123471 | S4: https://doi.org/10.1016/j.oceaneng.2025.123471 | V4: scopus | Y4: yes | AB4: verified_scopus | AC4: https://www.sciencedirect.com/author/57224792997/ulrik-dam-nielsen
A5: scopus-10-1109-lgrs-2026-3659009 | B5: 2026 | D5: Sentinel-1 Ground Truth Dataset for Coastline Extraction | E5: Gianpaolo Passarello; Sergio Vitale; Giampaolo Ferraioli; Vito Pascazio | F5: Giampaolo Ferraioli | G5: Journal Article | H5: IEEE Geoscience and Remote Sensing Letters | L5: 23 | O5: 10.1109/LGRS.2026.3659009 | P5: 10.1109/lgrs.2026.3659009 | S5: https://doi.org/10.1109/LGRS.2026.3659009 | V5: scopus | Y5: yes | AB5: verified_scopus | AC5: https://www.sciencedirect.com/author/7003486376/vito-pascazio
A6: scopus-10-1109-lgrs-2025-3555441 | B6: 2025 | D6: A Deep Learning Solution for Phase Screen Estimation in SAR Tomography | E6: Hossein Aghababaei; Giampaolo Ferraioli; Sergio Vitale; Alfred Stein | F6: Giampaolo Ferraioli | G6: Journal Article | H6: IEEE Geoscience and Remote Sensing Letters | L6: 22 | N6: 4007605 | O6: 10.1109/LGRS.2025.3555441 | P6: 10.1109/lgrs.2025.3555441 | S6: https://doi.org/10.1109/LGRS.2025.3555441 | V6: scopus | Y6: yes | AB6: verified_scopus_indirect | AC6: https://research.utwente.nl/en/publications/a-deep-learning-solution-for-phase-screen-estimation-in-sar-tomog/
A7: scopus-10-1109-metroaerospace64938-2025-11114485 | B7: 2025 | D7: A Micro Radar-Based Low-Cost Solution for Positioning and Detection, and Avoidance System | E7: Gennaro Ariante; Lucie Rocquelain; Salvatore Gaglione; Silvio Del Pizzo; Giuseppe Del Core | F7: Salvatore Gaglione; Silvio Del Pizzo | G7: Conference Paper | H7: 2025 IEEE International Workshop on Metrology for AeroSpace, MetroAeroSpace 2025 - Proceedings | O7: 10.1109/MetroAeroSpace64938.2025.11114485 | P7: 10.1109/metroaerospace64938.2025.11114485 | S7: https://www.scopus.com/inward/record.uri?eid=2-s2.0-105015377060&doi=10.1109%2fMetroAeroSpace64938.2025.11114485&partnerID=40&md5=03287e527efef9f4adf9d23e9c84507f | V7: scopus | Y7: yes | AA7: 2-s2.0-105015377060 | AB7: verified_scopus | AC7: https://www.scopus.com/inward/record.uri?eid=2-s2.0-105015377060&doi=10.1109%2fMetroAeroSpace64938.2025.11114485&partnerID=40&md5=03287e527efef9f4adf9d23e9c84507f
A8: scopus-10-1016-j-oceaneng-2025-121579 | B8: 2025 | D8: A numerical model of ship manoeuvring for the KVLCC2 hull, in regular and long-crested irregular waves | E8: Maria Acanfora; Marco Altosole; Silvia Pennino | F8: Silvia Pennino | G8: Journal Article | H8: Ocean Engineering | L8: 333 | N8: 121579 | O8: 10.1016/j.oceaneng.2025.121579 | P8: 10.1016/j.oceaneng.2025.121579 | S8: https://doi.org/10.1016/j.oceaneng.2025.121579 | V8: scopus | Y8: yes | AB8: verified_scopus | AC8: https://ouci.dntb.gov.ua/works/9Gmm8Yyx/
A9: scopus-10-1109-metrosea66681-2025-11245754 | B9: 2025 | D9: Advancing Offshore Renewable Energy in the Mediterranean Sea: Digital-Med, a Project for Integrating Resource Assessment and Decision Support | E9: Silvio Del Pizzo; Salvatore Gaglione; Pier Paolo Amoroso; Pasquale Contestabile; Yuri Cotroneo; Francesco Giuseppe Figliomeni; Diego Vicinanza; Giorgio Budillon | F9: Silvio Del Pizzo; Salvatore Gaglione | G9: Conference Paper | H9: 2025 IEEE International Workshop on Metrology for the Sea; Learning to Measure Sea Health Parameters, MetroSea 2025 - Proceedings | O9: 10.1109/MetroSea66681.2025.11245754 | P9: 10.1109/metrosea66681.2025.11245754 | S9: https://www.scopus.com/inward/record.uri?eid=2-s2.0-105029542122&doi=10.1109%2fMetroSea66681.2025.11245754&partnerID=40&md5=deea9b4f945a9ec20267bce45c30d977 | V9: scopus | Y9: yes | AA9: 2-s2.0-105029542122 | AB9: verified_scopus | AC9: https://www.scopus.com/inward/record.uri?eid=2-s2.0-105029542122&doi=10.1109%2fMetroSea66681.2025.11245754&partnerID=40&md5=deea9b4f945a9ec20267bce45c30d977
A10: scopus-10-1109-igarss55030-2025-11243038 | B10: 2025 | C10: 2025-08 | D10: An Open-Access Cross-Modal Forest Benchmark Training Dataset With Sentinel-1 and Lidar data | E10: Hossein Aghababaei; Giampaolo Ferraioli; Gilda Schirinzi; Erkki Tomppo; Jaan Praks | F10: Giampaolo Ferraioli | G10: Conference Paper | H10: IGARSS 2025 - 2025 IEEE International Geoscience and Remote Sensing Symposium | N10: 3588-3591 | O10: 10.1109/IGARSS55030.2025.11243038 | P10: 10.1109/igarss55030.2025.11243038 | S10: https://www.scopus.com/pages/publications/105034117757 | V10: scopus | Y10: yes | AA10: 2-s2.0-105034117757 | AB10: verified_scopus | AC10: https://research.aalto.fi/en/publications/an-open-access-cross-modal-forest-benchmark-training-dataset-with/
A11: scopus-10-1016-j-oceaneng-2025-122258 | B11: 2025 | C11: 2025-11-30 | D11: Assessment of bimodal sea states by the wave buoy analogy method | E11: Vincenzo Piscopo; Silvia Ascione; Antonio Scamardella | F11: Vincenzo Piscopo; Antonio Scamardella | G11: Journal Article | H11: Ocean Engineering | L11: 340 | M11: Part 1 | N11: 122258 | O11: 10.1016/j.oceaneng.2025.122258 | P11: 10.1016/j.oceaneng.2025.122258 | S11: https://doi.org/10.1016/j.oceaneng.2025.122258 | V11: scopus | Y11: yes | AB11: verified_scopus | AC11: https://www.sciencedirect.com/author/6507257720/v-piscopo
A12: scopus-10-1038-s41598-025-00653-8 | B12: 2025 | C12: 2025-05-12 | D12: Augustus’ solar meridian functioning and the birth of the western leap year | E12: V. Baiocchi; M. Baumgartner; M. Barbarella; M. T. D’Alessio; Silvio Del Pizzo; F. Giannone; F. Radicioni; A. Stoppini; G. Tosi; Salvatore Troisi; L. Alessandri | F12: Silvio Del Pizzo; Salvatore Troisi | G12: Journal Article | H12: Scientific Reports | L12: 15 | N12: 16463 | O12: 10.1038/s41598-025-00653-8 | P12: 10.1038/s41598-025-00653-8 | S12: https://doi.org/10.1038/s41598-025-00653-8 | V12: scopus | Y12: yes | AB12: verified_scopus_indirect | AC12: https://research.rug.nl/en/publications/augustus-solar-meridian-functioning-and-the-birth-of-the-western-/
A13: scopus-10-1109-mgrs-2025-3612752 | B13: 2025 | C13: 2025-12-17 | D13: IEEE Geoscience and Remote Sensing Society Awards Presented at the IEEE International Geoscience and Remote Sensing Symposium 2025 Awards Reception and Ceremony | E13: Francesca Bovolo; Jaya Sreevalsan-Nair; Antonio Plaza; Alberto Moreira; Giampaolo Ferraioli; Claudio Persello | F13: Giampaolo Ferraioli | G13: Conference Report | H13: IEEE Geoscience and Remote Sensing Magazine | L13: 13 | N13: 444-454 | O13: 10.1109/MGRS.2025.3612752 | P13: 10.1109/mgrs.2025.3612752 | S13: https://doi.org/10.1109/MGRS.2025.3612752 | V13: scopus | Y13: yes | AB13: verified_scopus | AC13: https://elib.dlr.de/222017/
A14: scopus-10-1109-mgrs-2025-3599367 | B14: 2025 | C14: 2025-12 | D14: IGARSS 2025 in Brisbane, Australia: Impressions of the First Days | E14: Alberto Moreira; Francesca Bovolo; Jaya Sreevalsan-Nair; Giampaolo Ferraioli | F14: Giampaolo Ferraioli | G14: Conference Report | H14: IEEE Geoscience and Remote Sensing Magazine | L14: 13 | M14: 4 | N14: 430-443 | O14: 10.1109/MGRS.2025.3599367 | P14: 10.1109/mgrs.2025.3599367 | S14: https://doi.org/10.1109/MGRS.2025.3599367 | V14: scopus | Y14: yes | AB14: verified_scopus | AC14: https://elib.dlr.de/218787/
A15: scopus-10-33012-2025-19984 | B15: 2025 | D15: The G4 Solar Storm of May 2024: Impact on the GNSS carrier-phase measurements | E15: Giovanni Cappello; Ciro Gioia; Antonio Angrisano; Gabriele Portelli; Salvatore Gaglione | F15: Salvatore Gaglione | G15: Conference Paper | H15: Proceedings of the International Technical Meeting of The Institute of Navigation, ITM | O15: 10.33012/2025.19984 | P15: 10.33012/2025.19984 | S15: https://www.scopus.com/inward/record.uri?eid=2-s2.0-105001675036&doi=10.33012%2f2025.19984&partnerID=40&md5=739f848160bb42247f9941f85f76ae90 | V15: scopus | Y15: yes | AA15: 2-s2.0-105001675036 | AB15: verified_scopus | AC15: https://www.scopus.com/inward/record.uri?eid=2-s2.0-105001675036&doi=10.33012%2f2025.19984&partnerID=40&md5=739f848160bb42247f9941f85f76ae90
A16: scopus-10-1109-metroaerospace64938-2025-11114637 | B16: 2025 | D16: The Galileo-based UAV velocity: Doppler and Time-Differenced Carrier Phase | E16: Giovanni Cappello; Ciro Gioia; Andrea Piccolo; Antonio Angrisano; Salvatore Gaglione | F16: Salvatore Gaglione | G16: Conference Paper | H16: 2025 IEEE International Workshop on Metrology for AeroSpace, MetroAeroSpace 2025 - Proceedings | O16: 10.1109/MetroAeroSpace64938.2025.11114637 | P16: 10.1109/metroaerospace64938.2025.11114637 | S16: https://www.scopus.com/inward/record.uri?eid=2-s2.0-105015510478&doi=10.1109%2fMetroAeroSpace64938.2025.11114637&partnerID=40&md5=7eb302fc7d501619ffc0077b7e307cfc | V16: scopus | Y16: yes | AA16: 2-s2.0-105015510478 | AB16: verified_scopus | AC16: https://www.scopus.com/inward/record.uri?eid=2-s2.0-105015510478&doi=10.1109%2fMetroAeroSpace64938.2025.11114637&partnerID=40&md5=7eb302fc7d501619ffc0077b7e307cfc
A17: scopus-10-33012-2025-19974 | B17: 2025 | D17: The synthetic meta-signal observations: a multipath resistance assessment | E17: Giovanni Cappello; Ciro Gioia; Antonio Angrisano; Salvatore Gaglione | F17: Salvatore Gaglione | G17: Conference Paper | H17: Proceedings of the International Technical Meeting of The Institute of Navigation, ITM | O17: 10.33012/2025.19974 | P17: 10.33012/2025.19974 | S17: https://www.scopus.com/inward/record.uri?eid=2-s2.0-105001668620&doi=10.33012%2f2025.19974&partnerID=40&md5=e3784e375792ec1833f2de6d00e0ea7b | V17: scopus | Y17: yes | AA17: 2-s2.0-105001668620 | AB17: verified_scopus | AC17: https://www.scopus.com/inward/record.uri?eid=2-s2.0-105001668620&doi=10.33012%2f2025.19974&partnerID=40&md5=e3784e375792ec1833f2de6d00e0ea7b
A18: scopus-10-3390-agriengineering7040120 | B18: 2025 | C18: 2025-04 | D18: Tomato Leaf Detection, Segmentation, and Extraction in Real-Time Environment for Accurate Disease Detection | E18: Shahab Ul Islam; Giampaolo Ferraioli; Vito Pascazio | F18: Giampaolo Ferraioli | G18: Journal Article | H18: AgriEngineering | L18: 7 | M18: 4 | N18: 120 | O18: 10.3390/agriengineering7040120 | P18: 10.3390/agriengineering7040120 | S18: https://doi.org/10.3390/agriengineering7040120 | V18: scopus | Y18: yes | AB18: verified_scopus | AC18: https://ouci.dntb.gov.ua/en/works/l111xP2y/
A19: scopus-10-3390-engproc2025088014 | B19: 2025 | D19: Toward Context-Aware GNSS Positioning: A Preliminary Analysis | E19: Giovanni Cappello; Antonio Maratea; Ciro Gioia; Antonio Angrisano; Silvio Del Pizzo; Salvatore Gaglione | F19: Silvio Del Pizzo; Salvatore Gaglione | G19: Journal Article | H19: Engineering Proceedings | L19: 88 | O19: 10.3390/engproc2025088014 | P19: 10.3390/engproc2025088014 | S19: https://www.scopus.com/inward/record.uri?eid=2-s2.0-105023666393&doi=10.3390%2fengproc2025088014&partnerID=40&md5=062a75da7c74085f6b1f50a1bc441882 | V19: scopus | Y19: yes | AA19: 2-s2.0-105023666393 | AB19: verified_scopus | AC19: https://www.scopus.com/inward/record.uri?eid=2-s2.0-105023666393&doi=10.3390%2fengproc2025088014&partnerID=40&md5=062a75da7c74085f6b1f50a1bc441882
A20: drupal-258 | B20: 2024 | D20: An Action-Camera Based Stereo System for MicroROV for Monitoring Coralline Algae in the Mediterranean Sea: Preliminary Assessment | E20: Silvio Del Pizzo; Erica Nocerino; Salvatore Gaglione; Alessio Calantropio; Fabio Menna; Salvatore Troisi | F20: Silvio Del Pizzo; Salvatore Gaglione; Salvatore Troisi | G20: Conference Paper | H20: 2024 IEEE International Workshop on Metrology for the Sea, MetroSea 2024 - Proceedings | O20: 10.1109/MetroSea62823.2024.10765774 | P20: 10.1109/MetroSea62823.2024.10765774 | S20: https://www.scopus.com/inward/record.uri?eid=2-s2.0-85214391242&doi=10.1109%2fMetroSea62823.2024.10765774&partnerID=40&md5=2d0c92ac8be583233e06effe4d12532f | U20: eng | V20: drupal | W20: 258 | X20: 1 | Y20: yes | AB20: legacy_drupal_historical
A21: drupal-256 | B21: 2024 | D21: Analysis of HAS performance in pedestrian navigation with different grade devices | E21: Antonio Angrisano; Milad Bagheri; Giovanni Cappello; Paolo Dabove; Silvio Del Pizzo; Salvatore Gaglione; Ciro Gioia; Gabriele Portelli; Salvatore Troisi | F21: Silvio Del Pizzo; Salvatore Gaglione; Salvatore Troisi | G21: Journal Article | H21: Proceedings of the International Technical Meeting of the Satellite Division of The Institute of Navigation, ION GNSS+ | N21: 2123 – 2135 | O21: 10.33012/2024.19785 | P21: 10.33012/2024.19785 | S21: https://www.scopus.com/inward/record.uri?eid=2-s2.0-105012766205&doi=10.33012%2f2024.19785&partnerID=40&md5=e81c13a01c9e0d13144add1c588eb12c | U21: eng | V21: drupal | W21: 256 | X21: 1 | Y21: yes | AB21: legacy_drupal_historical
A22: drupal-261 | B22: 2024 | D22: Correlation of Collision Damage Statistical Properties by Gaussian Copula Functions | E22: Salvatore Gaglione; Vincenzo Piscopo; Andrea Sciacca | F22: Salvatore Gaglione; Vincenzo Piscopo | G22: Conference Paper | H22: 2024 IEEE International Workshop on Metrology for the Sea, MetroSea 2024 - Proceedings | O22: 10.1109/MetroSea62823.2024.10765782 | P22: 10.1109/MetroSea62823.2024.10765782 | S22: https://www.scopus.com/inward/record.uri?eid=2-s2.0-85214363453&doi=10.1109%2fMetroSea62823.2024.10765782&partnerID=40&md5=14f1ce4e0d1531fda790a79b0eae0ad1 | U22: eng | V22: drupal | W22: 261 | X22: 1 | Y22: yes | AB22: legacy_drupal_historical
A23: drupal-259 | B23: 2024 | D23: GNSS-Based Velocity Measurement for Smart Mobility Systems | E23: Antonio Angrisano; Luigi Ferrigno; Salvatore Gaglione; Gianfranco Miele; Keerthana Velusamy | F23: Salvatore Gaglione | G23: Conference Paper | H23: 2024 IEEE International Symposium on Measurements and Networking, M and N 2024 - Proceedings | O23: 10.1109/MN60932.2024.10615589 | P23: 10.1109/MN60932.2024.10615589 | S23: https://www.scopus.com/inward/record.uri?eid=2-s2.0-85201282172&doi=10.1109%2fMN60932.2024.10615589&partnerID=40&md5=5ea07535af170ea0a0c98f82003e0e57 | U23: eng | V23: drupal | W23: 259 | X23: 1 | Y23: yes | AB23: legacy_drupal_historical
A24: drupal-257 | B24: 2024 | D24: Test of Galileo HAS in Precise Maritime Survey | E24: Antonio Angrisano; Giovanni Cappello; Silvio Del Pizzo; Salvatore Gaglione; Ciro Gioia; Gabriele Portelli; Salvatore Troisi | F24: Silvio Del Pizzo; Salvatore Gaglione; Salvatore Troisi | G24: Conference Paper | H24: 2024 IEEE International Workshop on Metrology for the Sea, MetroSea 2024 - Proceedings | O24: 10.1109/MetroSea62823.2024.10765743 | P24: 10.1109/MetroSea62823.2024.10765743 | S24: https://www.scopus.com/inward/record.uri?eid=2-s2.0-85214362769&doi=10.1109%2fMetroSea62823.2024.10765743&partnerID=40&md5=713959dc325e54a403184d6b7aadc894 | U24: eng | V24: drupal | W24: 257 | X24: 1 | Y24: yes | AB24: legacy_drupal_historical
A25: drupal-262 | B25: 2024 | D25: The 3d reconstruction of the sansevero chapel anatomical machines: A geomatics challenge | E25: Silvio Del Pizzo; Fabiana Di Ciaccio; Salvatore Gaglione; F.M. Galassi; V. Papa; E. Varotto; Salvatore Troisi | F25: Silvio Del Pizzo; Salvatore Gaglione; Salvatore Troisi | G25: Conference Paper | H25: International Archives of the Photogrammetry, Remote Sensing and Spatial Information Sciences - ISPRS Archives | O25: 10.5194/isprs-Archives-XLVIII-2-W4-2024-173-2024 | P25: 10.5194/isprs-Archives-XLVIII-2-W4-2024-173-2024 | S25: https://www.scopus.com/inward/record.uri?eid=2-s2.0-85186960308&doi=10.5194%2fisprs-Archives-XLVIII-2-W4-2024-173-2024&partnerID=40&md5=d5d299a56153d9ea77e6f6cd098e499e | U25: eng | V25: drupal | W25: 262 | X25: 1 | Y25: yes | AB25: legacy_drupal_historical
A26: drupal-260 | B26: 2024 | D26: Velocity Estimation Using Time-Differenced Carrier Phase and Doppler Shift with Different Grades of Devices: From Smartphones to Professional Receivers | E26: Antonio Angrisano; Giovanni Cappello; Salvatore Gaglione; Ciro Gioia | F26: Salvatore Gaglione | G26: Journal Article | H26: Algorithms | L26: 17 | O26: 10.3390/a17010002 | P26: 10.3390/a17010002 | S26: https://www.scopus.com/inward/record.uri?eid=2-s2.0-85183172433&doi=10.3390%2fa17010002&partnerID=40&md5=8afa55dd42780951d37d263b0eeaade4 | U26: eng | V26: drupal | W26: 260 | X26: 1 | Y26: yes | AB26: legacy_drupal_historical
A27: drupal-247 | B27: 2023 | D27: An Enhanced Photogrammetric Approach for the Underwater Surveying of the Posidonia Meadow Structure in the Spiaggia Nera Area of Maratea | E27: Francesca Russo; Silvio Del Pizzo; Fabiana Di Ciaccio; Salvatore Troisi | F27: Silvio Del Pizzo; Salvatore Troisi | G27: Journal Article | H27: Journal of Imaging | L27: 9 | N27: 113 | U27: eng | V27: drupal | W27: 247 | X27: 1 | Y27: yes | Z27: missing_doi | AB27: legacy_drupal_historical
A28: drupal-243 | B28: 2023 | D28: Application of “Galileo High Accuracy Service” on Single-Point Positioning | E28: Antonio Angrisano; Silvia Ascione; Giovanni Cappello; Ciro Gioia; Salvatore Gaglione | F28: Salvatore Gaglione | G28: Journal Article | H28: Sensors | L28: 23 | O28: 10.3390/s23094223 | P28: 10.3390/s23094223 | S28: https://www.scopus.com/inward/record.uri?eid=2-s2.0-85159187764&doi=10.3390%2fs23094223&partnerID=40&md5=ae572f6afd7651a924051f8c60baeda9 | U28: eng | V28: drupal | W28: 243 | X28: 1 | Y28: yes | AB28: legacy_drupal_historical
A29: drupal-254 | B29: 2023 | D29: Application of “Galileo High Accuracy Service” on Single-Point Positioning | E29: Antonio Angrisano; Silvia Ascione; Giovanni Cappello; Ciro Gioia; Salvatore Gaglione | F29: Salvatore Gaglione | G29: Journal Article | H29: Sensors | L29: 23 | O29: 10.3390/s23094223 | P29: 10.3390/s23094223 | S29: https://www.scopus.com/inward/record.uri?eid=2-s2.0-85159187764&doi=10.3390%2fs23094223&partnerID=40&md5=ae572f6afd7651a924051f8c60baeda9 | U29: eng | V29: drupal | W29: 254 | X29: 1 | Y29: yes | AB29: legacy_drupal_historical
A30: drupal-244 | B30: 2023 | D30: Demonstrating Galileo Has in Single Point Positioning | E30: Giovanni Cappello; Antonio Angrisano; Silvia Ascione; Silvio Del Pizzo; Ciro Gioia; Gabriele Portelli; Melania Susi; Salvatore Gaglione | F30: Silvio Del Pizzo; Salvatore Gaglione | G30: Conference Paper | H30: 2023 IEEE International Workshop on Metrology for Automotive (MetroAutomotive) | O30: 10.1109/MetroAutomotive57488.2023.10219138 | P30: 10.1109/MetroAutomotive57488.2023.10219138 | U30: eng | V30: drupal | W30: 244 | X30: 1 | Y30: yes | AB30: legacy_drupal_historical
A31: drupal-250 | B31: 2023 | D31: Enhancing navigation solution with Galileo HAS | E31: Gabriele Portelli; Antonio Angrisano; Giovanni Cappello; Silvio Del Pizzo; Ciro Gioia; Salvatore Troisi; Salvatore Gaglione | F31: Silvio Del Pizzo; Salvatore Troisi; Salvatore Gaglione | G31: Conference Paper | H31: 2023 IEEE International Workshop on Metrology for the Sea; Learning to Measure Sea Health Parameters, MetroSea 2023 - Proceedings | O31: 10.1109/MetroSea58055.2023.10317475 | P31: 10.1109/MetroSea58055.2023.10317475 | S31: https://www.scopus.com/inward/record.uri?eid=2-s2.0-85179760632&doi=10.1109%2fMetroSea58055.2023.10317475&partnerID=40&md5=4bdaad2f44110baa3a7f574c5fcca34e | U31: eng | V31: drupal | W31: 250 | X31: 1 | Y31: yes | AB31: legacy_drupal_historical
A32: drupal-245 | B32: 2023 | D32: Galileo-Based Doppler Shifts and Time Difference Carrier Phase: A Static Case Demonstration | E32: Ciro Gioia; Antonio Angrisano; Salvatore Gaglione | F32: Salvatore Gaglione | G32: Journal Article | H32: Sensors | L32: 23 | N32: 6828 | U32: eng | V32: drupal | W32: 245 | X32: 1 | Y32: yes | Z32: missing_doi | AB32: legacy_drupal_historical
A33: drupal-255 | B33: 2023 | D33: Galileo-Based Doppler Shifts and Time Difference Carrier Phase: A Static Case Demonstration | E33: Ciro Gioia; Antonio Angrisano; Salvatore Gaglione | F33: Salvatore Gaglione | G33: Journal Article | H33: Sensors | L33: 23 | O33: 10.3390/s23156828 | P33: 10.3390/s23156828 | S33: https://www.scopus.com/inward/record.uri?eid=2-s2.0-85167770866&doi=10.3390%2fs23156828&partnerID=40&md5=d69193446808e4fbeb3782abda0ab86b | U33: eng | V33: drupal | W33: 255 | X33: 1 | Y33: yes | AB33: legacy_drupal_historical
A34: drupal-234 | B34: 2023 | D34: Hydrodynamic Design of Fixed Hydrofoils for Planing Craft | E34: Egidio D’Amato; Immacolata Notaro; Vincenzo Piscopo; Antonio Scamardella | F34: Vincenzo Piscopo; Antonio Scamardella | G34: Journal Article | H34: Journal of Marine Science and Engineering | L34: 11 | O34: 10.3390/jmse11020246 | P34: 10.3390/jmse11020246 | S34: https://www.scopus.com/inward/record.uri?eid=2-s2.0-85149140611&doi=10.3390%2fjmse11020246&partnerID=40&md5=2cd47d37808972072d2e4a35a528c2ab | U34: eng | V34: drupal | W34: 234 | X34: 1 | Y34: yes | AB34: legacy_drupal_historical
A35: drupal-252 | B35: 2023 | D35: Incidence of parametrized methods for spectral analysis of Ship Motion | E35: Silvia Ascione; Salvatore Gaglione; Vincenzo Piscopo; Antonio Scamardella | F35: Salvatore Gaglione; Vincenzo Piscopo; Antonio Scamardella | G35: Conference Paper | H35: 2023 IEEE International Workshop on Metrology for the Sea; Learning to Measure Sea Health Parameters, MetroSea 2023 - Proceedings | O35: 10.1109/MetroSea58055.2023.10317389 | P35: 10.1109/MetroSea58055.2023.10317389 | S35: https://www.scopus.com/inward/record.uri?eid=2-s2.0-85179753312&doi=10.1109%2fMetroSea58055.2023.10317389&partnerID=40&md5=18038ff73c03b5a7fba74943e87e7bb8 | U35: eng | V35: drupal | W35: 252 | X35: 1 | Y35: yes | AB35: legacy_drupal_historical
A36: drupal-238 | B36: 2023 | D36: Motions Assessment Using a Time Domain Approach for a Research Ship in Antarctic Waters | E36: Silvia Pennino; Antonio Scamardella | F36: Silvia Pennino; Antonio Scamardella | G36: Journal Article | H36: Journal of Marine Science and Engineering | L36: 11 | O36: 10.3390/jmse11030558 | P36: 10.3390/jmse11030558 | S36: https://www.scopus.com/inward/record.uri?eid=2-s2.0-85151472339&doi=10.3390%2fjmse11030558&partnerID=40&md5=c0a42499d792671ff743c0f68da53828 | U36: eng | V36: drupal | W36: 238 | X36: 1 | Y36: yes | AB36: legacy_drupal_historical
A37: drupal-239 | B37: 2023 | D37: Neustrelitz Total Electron Content Model for Galileo Performance: A Position Domain Analysis | E37: Ciro Gioia; Antonio Angrisano; Salvatore Gaglione | F37: Salvatore Gaglione | G37: Journal Article | H37: Sensors (Basel, Switzerland) | L37: 23 | O37: 10.3390/s23073766 | P37: 10.3390/s23073766 | S37: https://www.scopus.com/inward/record.uri?eid=2-s2.0-85152305860&doi=10.3390%2fs23073766&partnerID=40&md5=fb7b82a05b8f07743fd2687f5cf0732c | U37: eng | V37: drupal | W37: 239 | X37: 1 | Y37: yes | AB37: legacy_drupal_historical
A38: drupal-253 | B38: 2023 | D38: Neustrelitz Total Electron Content Model for Galileo Performance: A Position Domain Analysis | E38: Ciro Gioia; Antonio Angrisano; Salvatore Gaglione | F38: Salvatore Gaglione | G38: Journal Article | H38: Sensors | L38: 23 | O38: 10.3390/s23073766 | P38: 10.3390/s23073766 | S38: https://www.scopus.com/inward/record.uri?eid=2-s2.0-85152305860&doi=10.3390%2fs23073766&partnerID=40&md5=fb7b82a05b8f07743fd2687f5cf0732c | U38: eng | V38: drupal | W38: 253 | X38: 1 | Y38: yes | AB38: legacy_drupal_historical
A39: drupal-246 | B39: 2023 | D39: Reconstructing anthropic coastal landscape of Campi Flegrei volcanic area (Southern Italy) during the Roman period from multi-technique surveys | E39: Gaia Mattei; Lucio Amato; Claudia Caporizzo; Aldo Cinque; Gerardo Pappone; Alessia Sorrentino; Paolo Stocchi; Salvatore Troisi; Pietro PC Aucelli | F39: Salvatore Troisi | G39: Journal Article | H39: Journal of Maps | N39: 1–14 | U39: eng | V39: drupal | W39: 246 | X39: 1 | Y39: yes | Z39: ambiguous_author:Aucelli, Pietro PC; missing_doi | AB39: legacy_drupal_historical
A40: drupal-251 | B40: 2023 | D40: Reliability of Smartphone Positioning in Harsh Environment † | E40: Giovanni Cappello; Ciro Gioia; Antonio Angrisano; Silvio Del Pizzo; Gabriele Portelli; Salvatore Gaglione | F40: Silvio Del Pizzo; Salvatore Gaglione | G40: Journal Article | H40: Engineering Proceedings | L40: 54 | O40: 10.3390/ENC2023-15429 | P40: 10.3390/ENC2023-15429 | S40: https://www.scopus.com/inward/record.uri?eid=2-s2.0-85186439748&doi=10.3390%2fENC2023-15429&partnerID=40&md5=2140d47215ca7c12bf2c156d766cae6c | U40: eng | V40: drupal | W40: 251 | X40: 1 | Y40: yes | AB40: legacy_drupal_historical
A41: drupal-233 | B41: 2023 | D41: Ultimate strength assessment of simply supported pitted platings: A new stochastic approach based on Monte Carlo simulation | E41: Vincenzo Piscopo; Antonio Scamardella | F41: Vincenzo Piscopo; Antonio Scamardella | G41: Journal Article | H41: Marine Structures | L41: 87 | O41: 10.1016/j.marstruc.2022.103312 | P41: 10.1016/j.marstruc.2022.103312 | S41: https://www.scopus.com/inward/record.uri?eid=2-s2.0-85140736245&doi=10.1016%2fj.marstruc.2022.103312&partnerID=40&md5=d5db091d4192716c279eaf3b3317fbe1 | U41: eng | V41: drupal | W41: 233 | X41: 1 | Y41: yes | AB41: legacy_drupal_historical
A42: drupal-237 | B42: 2022 | D42: A flexible and swift approach for 3D image–based survey in a cave | E42: L. Alessandri; Valerio Baiocchi; Silvio Del Pizzo; Fabiana Di Ciaccio; Matteo Onori; M.F. Rolfo; Salvatore Troisi | F42: Silvio Del Pizzo; Salvatore Troisi | G42: Journal Article | H42: Applied Geomatics | L42: 14 | N42: 5 – 19 | O42: 10.1007/s12518-020-00309-4 | P42: 10.1007/s12518-020-00309-4 | S42: https://www.scopus.com/inward/record.uri?eid=2-s2.0-85084596892&doi=10.1007%2fs12518-020-00309-4&partnerID=40&md5=b4e5eb343d5ab1cdd990f9f70a0466fd | U42: eng | V42: drupal | W42: 237 | X42: 1 | Y42: yes | AB42: legacy_drupal_historical
A43: drupal-229 | B43: 2022 | D43: A New Orbiting Deployable System for Small Satellite Observations for Ecology and Earth Observation | E43: Elena Martellato; Alice Maria Piccirillo; Giampaolo Ferraioli; Alessandra Rotundi; Vincenzo Della Corte; Pasquale Palumbo; Emanuele Alcaras; Luca Appolloni; Giuseppe Aulicino; Ivano Bertini; Vincenzo Capozzi; Elena Catucci; Zelia Dionnet; Pasquale Di Palma; Flavio Esposito; Emanuele Ferrentino; Anna Innac; Laura Inno; Silvia Pennino; Simona Saviano; Giuseppina Tirimberio; Stefania Campopiano; Elena Chianese; Pier Paolo Franzese; Giannetta Fusco; Salvatore Gaglione; Agostino Iadicicco; Ferdinando Nunziata; Claudio Parente; Vincenzo Piscopo; Angelo Riccio; Giovanni Fulvio Russo; Enrico Zambianchi | F43: Giampaolo Ferraioli; Silvia Pennino; Salvatore Gaglione; Vincenzo Piscopo | G43: Journal Article | H43: Remote Sensing | L43: 14 | O43: 10.3390/rs14092066 | P43: 10.3390/rs14092066 | S43: https://www.scopus.com/inward/record.uri?eid=2-s2.0-85130569568&doi=10.3390%2frs14092066&partnerID=40&md5=c402d749c1d839052ece462d7d7c81f0 | U43: eng | V43: drupal | W43: 229 | X43: 1 | Y43: yes | AB43: legacy_drupal_historical
A44: drupal-227 | B44: 2022 | D44: DOP analysis using AIS R-MODE stations combined with GNSS satellites into the Venice Lagoon | E44: Antonio Angrisano; Silvia Ascione; Giovanni Cappello; Silvio Del Pizzo; Sebastiano Messina; Salvatore Gaglione | F44: Silvio Del Pizzo; Salvatore Gaglione | G44: Conference Paper | H44: 2022 IEEE International Workshop on Metrology for the Sea; Learning to Measure Sea Health Parameters, MetroSea 2022 - Proceedings | O44: 10.1109/MetroSea55331.2022.9950793 | P44: 10.1109/MetroSea55331.2022.9950793 | S44: https://www.scopus.com/inward/record.uri?eid=2-s2.0-85143665232&doi=10.1109%2fMetroSea55331.2022.9950793&partnerID=40&md5=73ad612f4cb4edc5ec1f0c12ca474447 | U44: eng | V44: drupal | W44: 227 | X44: 1 | Y44: yes | AB44: legacy_drupal_historical
A45: drupal-228 | B45: 2022 | D45: Enhanced geomatic techniques for the deformation survey of ship platings in a real environment | E45: Silvia Ascione; Silvio Del Pizzo; Salvatore Gaglione; Vincenzo Piscopo; Salvatore Troisi | F45: Silvio Del Pizzo; Salvatore Gaglione; Vincenzo Piscopo; Salvatore Troisi | G45: Conference Paper | H45: 2022 IEEE International Workshop on Metrology for the Sea; Learning to Measure Sea Health Parameters, MetroSea 2022 - Proceedings | O45: 10.1109/MetroSea55331.2022.9950828 | P45: 10.1109/MetroSea55331.2022.9950828 | S45: https://www.scopus.com/inward/record.uri?eid=2-s2.0-85143729681&doi=10.1109%2fMetroSea55331.2022.9950828&partnerID=40&md5=3bb6e244b742f567a5b21f7d191fb83f | U45: eng | V45: drupal | W45: 228 | X45: 1 | Y45: yes | AB45: legacy_drupal_historical
A46: drupal-231 | B46: 2022 | D46: Fatigue Assessment of Moorings for Floating Offshore Wind Turbines by Advanced Spectral Analysis Methods | E46: Vincenzo Piscopo; Antonio Scamardella; Giovanni Battista Rossi; Francesco Crenna; Marta Berardengo | F46: Vincenzo Piscopo; Antonio Scamardella | G46: Journal Article | H46: Journal of Marine Science and Engineering | L46: 10 | O46: 10.3390/jmse10010037 | P46: 10.3390/jmse10010037 | S46: https://www.scopus.com/inward/record.uri?eid=2-s2.0-85122727156&doi=10.3390%2fjmse10010037&partnerID=40&md5=6febaa2c13717be4da55277ec645b29d | U46: eng | V46: drupal | W46: 231 | X46: 1 | Y46: yes | AB46: legacy_drupal_historical
A47: drupal-230 | B47: 2022 | D47: Measurement of sea waves | E47: Giovanni Battista Rossi; Andrea Cannata; Antonio Iengo; Maurizio Migliaccio; Gabriele Nardone; Vincenzo Piscopo; Enrico Zambianchi | F47: Vincenzo Piscopo | G47: Journal Article | H47: Sensors | L47: 22 | O47: 10.3390/s22010078 | P47: 10.3390/s22010078 | S47: https://www.scopus.com/inward/record.uri?eid=2-s2.0-85121513512&doi=10.3390%2fs22010078&partnerID=40&md5=ac685f481b19ebcd98336868ac81ad97 | U47: eng | V47: drupal | W47: 230 | X47: 1 | Y47: yes | AB47: legacy_drupal_historical
A48: drupal-236 | B48: 2022 | D48: Monitoring the Posidonia Meadows structure through underwater photogrammetry: A case study | E48: Francesca Russo; Silvio Del Pizzo; Fabiana Di Ciaccio; Salvatore Troisi | F48: Silvio Del Pizzo; Salvatore Troisi | G48: Conference Paper | H48: 2022 IEEE International Workshop on Metrology for the Sea; Learning to Measure Sea Health Parameters, MetroSea 2022 - Proceedings | O48: 10.1109/MetroSea55331.2022.9950873 | P48: 10.1109/MetroSea55331.2022.9950873 | S48: https://www.scopus.com/inward/record.uri?eid=2-s2.0-85143730388&doi=10.1109%2fMetroSea55331.2022.9950873&partnerID=40&md5=972b07d1b354f67ed41b43f8da074c5d | U48: eng | V48: drupal | W48: 236 | X48: 1 | Y48: yes | AB48: legacy_drupal_historical
A49: drupal-232 | B49: 2022 | D49: Sensitivity Analysis of a Marine Gasoline Engine: From Power to Emissions | E49: Luigia Mocerino; Vincenzo Piscopo; Antonio Scamardella | F49: Vincenzo Piscopo; Antonio Scamardella | G49: Conference Paper | H49: Progress in Marine Science and Technology | O49: 10.3233/PMST220026 | P49: 10.3233/PMST220026 | S49: https://www.scopus.com/inward/record.uri?eid=2-s2.0-85138172002&doi=10.3233%2fPMST220026&partnerID=40&md5=6a23a661e912bb65f5bdb7b76ada7bf0 | U49: eng | V49: drupal | W49: 232 | X49: 1 | Y49: yes | AB49: legacy_drupal_historical
A50: drupal-220 | B50: 2022 | D50: Smartphone GNSS Performance in an Urban Scenario with RAIM Application | E50: Antonio Angrisano; Salvatore Gaglione | F50: Salvatore Gaglione | G50: Journal Article | H50: Sensors | L50: 22 | O50: 10.3390/s22030786 | P50: 10.3390/s22030786 | S50: https://www.scopus.com/inward/record.uri?eid=2-s2.0-85122911041&doi=10.3390%2fs22030786&partnerID=40&md5=2257427f4a504f1e14a0ee8098b8517e | U50: eng | V50: drupal | W50: 220 | X50: 1 | Y50: yes | AB50: legacy_drupal_historical
A51: drupal-235 | B51: 2022 | D51: Solutions and limitations of the geomatic survey of an archaeological site in hard to access areas with a latest generation smartphone: the example of the Intihuatana stone in Machu Picchu (Peru) | E51: Valerio Baiocchi; Silvio Del Pizzo; Felicia Monti; Giovanni Pugliano; Matteo Onori; Umberto Robustelli; Salvatore Troisi; Felicia Vatore; Francisco James León Trujillo | F51: Silvio Del Pizzo; Salvatore Troisi | G51: Journal Article | H51: Acta IMEKO | L51: 11 | O51: 10.21014/acta_imeko.v11i1.1117 | P51: 10.21014/acta_imeko.v11i1.1117 | S51: https://www.scopus.com/inward/record.uri?eid=2-s2.0-85128163308&doi=10.21014%2facta_imeko.v11i1.1117&partnerID=40&md5=8310bea6a52fc77f2b4da19e4bf790fd | U51: eng | V51: drupal | W51: 235 | X51: 1 | Y51: yes | Z51: ambiguous_author:Pizzo, Silvio Del | AB51: legacy_drupal_historical
A52: drupal-218 | B52: 2022 | D52: The EGNOS Augmentation in Maritime Navigation | E52: Anna Innac; Antonio Angrisano; Silvio Del Pizzo; Giovanni Cappello; Salvatore Gaglione | F52: Silvio Del Pizzo; Salvatore Gaglione | G52: Journal Article | H52: Sensors | L52: 22 | O52: 10.3390/s22030775 | P52: 10.3390/s22030775 | S52: https://www.scopus.com/inward/record.uri?eid=2-s2.0-85123544870&doi=10.3390%2fs22030775&partnerID=40&md5=4f9f702ca89cf3ec4f08c1e47634a44f | U52: eng | V52: drupal | W52: 218 | X52: 1 | Y52: yes | AB52: legacy_drupal_historical
A53: drupal-226 | B53: 2022 | D53: Time-Differenced Carrier Phase Technique for Precise Velocity Estimation on an Android Smartphone | E53: Antonio Angrisano; Giovanni Cappello; Silvio Del Pizzo; Salvatore Gaglione | F53: Silvio Del Pizzo; Salvatore Gaglione | G53: Journal Article | H53: Sensors | L53: 22 | O53: 10.3390/s22218514 | P53: 10.3390/s22218514 | S53: https://www.scopus.com/inward/record.uri?eid=2-s2.0-85141576490&doi=10.3390%2fs22218514&partnerID=40&md5=58bb5fe85b4ff343feeb6f5af0ade089 | U53: eng | V53: drupal | W53: 226 | X53: 1 | Y53: yes | AB53: legacy_drupal_historical
A54: drupal-172 | B54: 2021 | D54: A Kalman filter single point positioning for maritime applications using a smartphone | E54: Anna Innac; Antonio Angrisano; G. Dardanelli; Vincenzo Della Corte; Elena Martellato; Alessandra Rotundi; Giampaolo Ferraioli; Pasquale Palumbo; Salvatore Gaglione | F54: Giampaolo Ferraioli; Salvatore Gaglione | G54: Journal Article | H54: Geographia Technica | L54: 16 | N54: 15-29 | O54: 10.21163/GT_2021.163.02 | P54: 10.21163/GT_2021.163.02 | S54: https://www.scopus.com/inward/record.uri?eid=2-s2.0-85104946254&doi=10.21163%2fGT_2021.163.02&partnerID=40&md5=ee32f4e7818feeb22ee5c1c25d7e0419 | U54: eng | V54: drupal | W54: 172 | X54: 1 | Y54: yes | AB54: legacy_drupal_historical
A55: drupal-192 | B55: 2021 | D55: A preliminary study on an optical system for nautical and maritime traffic monitoring | E55: Silvio Del Pizzo; Salvatore Troisi; Antonio Angrisano; Fabiana Di Ciaccio; Salvatore Gaglione | F55: Silvio Del Pizzo; Salvatore Troisi; Salvatore Gaglione | G55: Conference Paper | H55: 2021 International Workshop on Metrology for the Sea; Learning to Measure Sea Health Parameters (MetroSea) | O55: 10.1109/MetroSea52177.2021.9611575 | P55: 10.1109/MetroSea52177.2021.9611575 | U55: eng | V55: drupal | W55: 192 | X55: 1 | Y55: yes | Z55: ambiguous_author:Pizzo, Silvio Del | AB55: legacy_drupal_historical
A56: drupal-197 | B56: 2021 | D56: Danae++: A smart approach for denoising underwater attitude estimation | E56: P. Russo; Fabiana Di Ciaccio; Salvatore Troisi | F56: Salvatore Troisi | G56: Journal Article | H56: Sensors | L56: 21 | N56: 1-21 | O56: 10.3390/s21041526 | P56: 10.3390/s21041526 | S56: https://www.scopus.com/inward/record.uri?eid=2-s2.0-85101177509&doi=10.3390%2fs21041526&partnerID=40&md5=aacf41a8b089e0745bbee8259b6a4861 | U56: eng | V56: drupal | W56: 197 | X56: 1 | Y56: yes | AB56: legacy_drupal_historical
A57: drupal-194 | B57: 2021 | D57: EGNOS Performances assessment in maritime navigation | E57: Anna Innac; Antonio Angrisano; Silvio Del Pizzo; Mario Vultaggio; Salvatore Gaglione | F57: Silvio Del Pizzo; Salvatore Gaglione | G57: Conference Paper | H57: 2021 International Workshop on Metrology for the Sea; Learning to Measure Sea Health Parameters (MetroSea) | O57: 10.1109/MetroSea52177.2021.9611552 | P57: 10.1109/MetroSea52177.2021.9611552 | U57: eng | V57: drupal | W57: 194 | X57: 1 | Y57: yes | Z57: ambiguous_author:Pizzo, Silvio Del | AB57: legacy_drupal_historical
A58: drupal-196 | B58: 2021 | D58: Monitoring marine environments with Autonomous Underwater Vehicles: A bibliometric analysis | E58: Fabiana Di Ciaccio; Salvatore Troisi | F58: Salvatore Troisi | G58: Journal Article | H58: Results in Engineering | L58: 9 | O58: 10.1016/j.rineng.2021.100205 | P58: 10.1016/j.rineng.2021.100205 | S58: https://www.scopus.com/inward/record.uri?eid=2-s2.0-85100073203&doi=10.1016%2fj.rineng.2021.100205&partnerID=40&md5=212378979419f0ca269c82a38c140075 | U58: eng | V58: drupal | W58: 196 | X58: 1 | Y58: yes | AB58: legacy_drupal_historical
A59: drupal-193 | B59: 2021 | D59: Photogrammetry applications on stranded cetaceans: fin whale case study and preliminary results. | E59: Silvio Del Pizzo; Salvatore Troisi; Rosa Linda Testa; Giuseppe Sciancalepore; Davide Pedrotti; Guido Pietroluongo | F59: Silvio Del Pizzo; Salvatore Troisi | G59: Conference Paper | H59: 2021 International Workshop on Metrology for the Sea; Learning to Measure Sea Health Parameters (MetroSea) | O59: 10.1109/MetroSea52177.2021.9611588 | P59: 10.1109/MetroSea52177.2021.9611588 | U59: eng | V59: drupal | W59: 193 | X59: 1 | Y59: yes | Z59: ambiguous_author:Pizzo, Silvio Del; ambiguous_author:Testa, Rosa Linda | AB59: legacy_drupal_historical
A60: drupal-195 | B60: 2021 | D60: Reconstructing the Late Pleistocene – Anthropocene interaction between the neotectonic and archaeological landscape evolution in the Apennines (La Sassa cave, Italy) | E60: L. Alessandri; G.L. Cardello; P.A.J. Attema; Valerio Baiocchi; F. De Angelis; Silvio Del Pizzo; Fabiana Di Ciaccio; A. Fiorillo; M. Gatta; Felicia Monti; Matteo Onori; M.F. Rolfo; M. Romboni; G. Sottili; Salvatore Troisi | F60: Silvio Del Pizzo; Salvatore Troisi | G60: Journal Article | H60: Quaternary Science Reviews | L60: 265 | O60: 10.1016/j.quascirev.2021.107067 | P60: 10.1016/j.quascirev.2021.107067 | S60: https://www.scopus.com/inward/record.uri?eid=2-s2.0-85109153117&doi=10.1016%2fj.quascirev.2021.107067&partnerID=40&md5=3b194a70e40e6d3cab1df4851e58b920 | U60: eng | V60: drupal | W60: 195 | X60: 1 | Y60: yes | AB60: legacy_drupal_historical
A61: drupal-171 | B61: 2021 | D61: Sea State Monitoring by Ship Motion Measurements Onboard a Research Ship in the Antarctic Waters | E61: Silvia Pennino; Antonio Angrisano; Vincenzo Della Corte; Giampaolo Ferraioli; Salvatore Gaglione; Anna Innac; Elena Martellato; Pasquale Palumbo; Vincenzo Piscopo; Alessandra Rotundi; Antonio Scamardella | F61: Silvia Pennino; Giampaolo Ferraioli; Salvatore Gaglione; Vincenzo Piscopo; Antonio Scamardella | G61: Journal Article | H61: Journal of Marine Science and Engineering | L61: 9 | N61: 64 | O61: 10.3390/jmse9010064 | P61: 10.3390/jmse9010064 | Q61: 2077-1312 | S61: https://www.mdpi.com/2077-1312/9/1/64 | T61: A parametric wave spectrum resembling procedure is applied to detect the sea state parameters, namely the wave peak period and significant wave height, based on the measurement and analysis of the heave and pitch motions of a vessel in a seaway, recorded by a smartphone located onboard the ship. The measurement system makes it possible to determine the heave and pitch acceleration spectra of the reference ship in the encounter frequency domain and, subsequently, the absolute sea spectra once the ship motion transfer functions are provided. The measurements have been carried out onboard the research ship “Laura Bassi”, during the oceanographic campaign in the Antarctic Ocean carried out in January and February 2020. The resembled sea spectra are compared with the weather forecast data, provided by the global-WAM (GWAM) model, in order to validate the sea spectrum resembling procedure. | U61: eng | V61: drupal | W61: 171 | X61: 1 | Y61: yes | AB61: legacy_drupal_historical
A62: drupal-204 | B62: 2020 | D62: A flexible and swift approach for 3D image–based survey in a cave | E62: L. Alessandri; Valerio Baiocchi; Silvio Del Pizzo; Fabiana Di Ciaccio; Matteo Onori; M.F. Rolfo; Salvatore Troisi | F62: Silvio Del Pizzo; Salvatore Troisi | G62: Journal Article | H62: Applied Geomatics | O62: 10.1007/s12518-020-00309-4 | P62: 10.1007/s12518-020-00309-4 | S62: https://www.scopus.com/inward/record.uri?eid=2-s2.0-85084596892&doi=10.1007%2fs12518-020-00309-4&partnerID=40&md5=b4e5eb343d5ab1cdd990f9f70a0466fd | U62: eng | V62: drupal | W62: 204 | X62: 1 | Y62: yes | AB62: legacy_drupal_historical
A63: drupal-161 | B63: 2020 | D63: A Machine Learning Approach for Walker Identification Using Smartphone Sensors | E63: Antonio Angrisano; P. Ardimento; M.L. Bernardi; M. Cimitile; Salvatore Gaglione | F63: Salvatore Gaglione | G63: Journal Article | H63: Studies in Computational Intelligence | L63: 880 | N63: 229-247 | O63: 10.1007/978-3-030-36617-9_14 | P63: 10.1007/978-3-030-36617-9_14 | Q63: 1860949X | S63: https://www.scopus.com/inward/record.uri?eid=2-s2.0-85078103442&doi=10.1007%2f978-3-030-36617-9_14&partnerID=40&md5=d6b9b3418dc0a28bea3cf61f6f4c08c5 | U63: eng | V63: drupal | W63: 161 | X63: 1 | Y63: yes | AB63: legacy_drupal_historical
A64: drupal-162 | B64: 2020 | D64: A new wave spectrum resembling procedure based on ship motion analysis | E64: Vincenzo Piscopo; Antonio Scamardella; Salvatore Gaglione | F64: Vincenzo Piscopo; Antonio Scamardella; Salvatore Gaglione | G64: Journal Article | H64: Ocean Engineering | L64: 201 | O64: 10.1016/j.oceaneng.2020.107137 | P64: 10.1016/j.oceaneng.2020.107137 | Q64: 00298018 | S64: https://www.scopus.com/inward/record.uri?eid=2-s2.0-85079837856&doi=10.1016%2fj.oceaneng.2020.107137&partnerID=40&md5=a1e0e8d7d2c0a6ab3b7a53fb7151c7a3 | U64: eng | V64: drupal | W64: 162 | X64: 1 | Y64: yes | AB64: legacy_drupal_historical
A65: drupal-203 | B65: 2020 | D65: A Preliminary Study on Attitude Measurement Systems Based on Low Cost Sensors | E65: Fabiana Di Ciaccio; Salvatore Gaglione; Salvatore Troisi | F65: Salvatore Gaglione; Salvatore Troisi | G65: Journal Article | H65: Communications in Computer and Information Science | L65: 1246 | N65: 103-115 | O65: 10.1007/978-3-030-62800-0_9 | P65: 10.1007/978-3-030-62800-0_9 | S65: https://www.scopus.com/inward/record.uri?eid=2-s2.0-85097387204&doi=10.1007%2f978-3-030-62800-0_9&partnerID=40&md5=df40a6ba8024aca29b08a45d61cafb52 | U65: eng | V65: drupal | W65: 203 | X65: 1 | Y65: yes | AB65: legacy_drupal_historical
A66: drupal-164 | B66: 2020 | D66: Absolute sea spectrum resampling from encounter wave time history | E66: Salvatore Gaglione; Silvia Pennino; Vincenzo Piscopo; Antonio Scamardella | F66: Salvatore Gaglione; Silvia Pennino; Vincenzo Piscopo; Antonio Scamardella | G66: Conference Paper | H66: 2019 IMEKO TC19 International Workshop on Metrology for the Sea: Learning to Measure Sea Health Parameters, MetroSea 2019 | R66: 9789299008423 | S66: https://www.scopus.com/inward/record.uri?eid=2-s2.0-85081048777&partnerID=40&md5=9d4ba859d16567adf7b39636ebaff725 | U66: eng | V66: drupal | W66: 164 | X66: 1 | Y66: yes | Z66: missing_doi | AB66: legacy_drupal_historical
A67: drupal-201 | B67: 2020 | D67: Ancient coastal changes due to ground movements and human interventions in the roman portus julius (Pozzuoli Gulf, Italy): Results from photogrammetric and direct surveys | E67: Pietro PC Aucelli; Gaia Mattei; Claudia Caporizzo; Aldo Cinque; Salvatore Troisi; F. Peluso; M. Stefanile; Gerardo Pappone | F67: Salvatore Troisi | G67: Journal Article | H67: Water (Switzerland) | L67: 12 | O67: 10.3390/w12030658 | P67: 10.3390/w12030658 | S67: https://www.scopus.com/inward/record.uri?eid=2-s2.0-85082705897&doi=10.3390%2fw12030658&partnerID=40&md5=d9bf0d02274de8fc28558d919b54f019 | U67: eng | V67: drupal | W67: 201 | X67: 1 | Y67: yes | Z67: ambiguous_author:Aucelli, P.P.C. | AB67: legacy_drupal_historical
A68: drupal-221 | B68: 2020 | D68: Assessment of shoreline detection using UAV | E68: Silvio Del Pizzo; Antonio Angrisano; Salvatore Gaglione; Salvatore Troisi | F68: Silvio Del Pizzo; Salvatore Gaglione; Salvatore Troisi | G68: Conference Paper | H68: MetroSea 2020 - TC19 International Workshop on Metrology for the Sea | S68: https://www.scopus.com/inward/record.uri?eid=2-s2.0-85123306702&partnerID=40&md5=a1327b0f2f73c11a700c7c1e82af4feb | U68: eng | V68: drupal | W68: 221 | X68: 1 | Y68: yes | Z68: ambiguous_author:Pizzo, S.D.; missing_doi | AB68: legacy_drupal_historical
A69: drupal-167 | B69: 2020 | C69: 2020 | D69: Development of a new ship adaptive weather routing model based on seakeeping analysis and optimization | E69: Silvia Pennino; Salvatore Gaglione; Anna Innac; Vincenzo Piscopo; Antonio Scamardella | F69: Silvia Pennino; Salvatore Gaglione; Vincenzo Piscopo; Antonio Scamardella | G69: Journal Article | H69: Journal of Marine Science and Engineering | L69: 8 | M69: 4 | R69: 20771312 (ISSN) | S69: https://www.scopus.com/inward/record.uri?eid=2-s2.0-85084633120&doi=10.3390%2fJMSE8040270&partnerID=40&md5=73cbf2170e262702db1ad7f10416663a | U69: eng | V69: drupal | W69: 167 | X69: 1 | Y69: yes | Z69: missing_doi | AB69: legacy_drupal_historical
A70: drupal-163 | B70: 2020 | D70: GPS precise positioning techniques for remote marine applications | E70: Anna Innac; Antonio Angrisano; Salvatore Gaglione; N. Crocetto | F70: Salvatore Gaglione | G70: Conference Paper | H70: 2019 IMEKO TC19 International Workshop on Metrology for the Sea: Learning to Measure Sea Health Parameters, MetroSea 2019 | R70: 9789299008423 | S70: https://www.scopus.com/inward/record.uri?eid=2-s2.0-85081056598&partnerID=40&md5=e70d4becb4ed1549b1a700a1708cab1d | U70: eng | V70: drupal | W70: 163 | X70: 1 | Y70: yes | Z70: missing_doi | AB70: legacy_drupal_historical
A71: drupal-165 | B71: 2020 | D71: Identification of Walker Identity Using Smartphone Sensors: An Experiment Using Ensemble Learning | E71: Antonio Angrisano; M.L. Bernardi; M. Cimitile; Salvatore Gaglione; Mario Vultaggio | F71: Salvatore Gaglione | G71: Journal Article | H71: IEEE Access | L71: 8 | N71: 27435-27447 | O71: 10.1109/ACCESS.2020.2971693 | P71: 10.1109/ACCESS.2020.2971693 | Q71: 21693536 | S71: https://www.scopus.com/inward/record.uri?eid=2-s2.0-85081113005&doi=10.1109%2fACCESS.2020.2971693&partnerID=40&md5=6df7e32b9ef02594f961428d88e5abc3 | U71: eng | V71: drupal | W71: 165 | X71: 1 | Y71: yes | AB71: legacy_drupal_historical
A72: drupal-202 | B72: 2020 | D72: Innovative Technologies for Coastal Paleo-Landscape Reconstruction and Paleo-Sea Level Measuring | E72: Gaia Mattei; Pietro PC Aucelli; Claudia Caporizzo; F. Peluso; Gerardo Pappone; Salvatore Troisi | F72: Salvatore Troisi | G72: Journal Article | H72: Communications in Computer and Information Science | L72: 1246 | N72: 244-255 | O72: 10.1007/978-3-030-62800-0_19 | P72: 10.1007/978-3-030-62800-0_19 | S72: https://www.scopus.com/inward/record.uri?eid=2-s2.0-85097429704&doi=10.1007%2f978-3-030-62800-0_19&partnerID=40&md5=7f1c19ead6e5a2f361a9b5e9b2f99b6f | U72: eng | V72: drupal | W72: 202 | X72: 1 | Y72: yes | Z72: ambiguous_author:Aucelli, P.P.C. | AB72: legacy_drupal_historical
A73: drupal-198 | B73: 2020 | D73: Integrated geomatic techniques for georeferencing and reconstructing the position of underground archaeological sites: The case study of the augustus sundial (rome) | E73: Valerio Baiocchi; R. Brigante; Silvio Del Pizzo; F. Giannone; Matteo Onori; F. Radicioni; A. Stoppini; G. Tosi; Salvatore Troisi; M. Baumgartner | F73: Silvio Del Pizzo; Salvatore Troisi | G73: Journal Article | H73: Remote Sensing | L73: 12 | N73: 1-17 | O73: 10.3390/rs12244064 | P73: 10.3390/rs12244064 | S73: https://www.scopus.com/inward/record.uri?eid=2-s2.0-85098263076&doi=10.3390%2frs12244064&partnerID=40&md5=72ed63037764b198293a3607405fc641 | U73: eng | V73: drupal | W73: 198 | X73: 1 | Y73: yes | AB73: legacy_drupal_historical
A74: drupal-169 | B74: 2020 | C74: 2020/05/11 | D74: Machine learning based LOS/NLOS classifier and robust estimator for GNSS shadow matching | E74: Haosheng Xu; Antonio Angrisano; Salvatore Gaglione; Li-Ta Hsu | F74: Salvatore Gaglione | G74: Journal Article | L74: 1 | M74: 1 | N74: 15 | R74: 2662-1363 | S74: https://doi.org/10.1186/s43020-020-00016-w | T74: Global Navigation Satellites Systems (GNSS) is frequently used for positioning services in various applications, e.g., pedestrian and vehicular navigation. However, it is well-known that GNSS positioning performs unreliably in urban environments. GNSS shadow matching is a method of improving accuracy in the cross-street direction. Initial position and classification of observed satellite visibility between line-of-sight (LOS) and non-line-of-sight (NLOS) are essential for its performance. For the conventional LOS/NLOS classification, the classifiers are based on a single feature, extracted from raw GNSS measurements, such as signal noise ratio, pseudorange, elevation angle, etc. Especially in urban canyons, these measurements are unstable and unreliable due to the signal reflection and refraction from the surrounding buildings. Besides, the conventional least square approach for positioning is insufficient to provide accurate initialization for shadow matching in urban areas. In our study, shadow matching is improved using the initial position from robust estimator and the satellite visibility determined by support vector machine (SVM). The robust estimator has an improved positioning accuracy and the classification rate of SVM classification can reach 91.5% in urban scenarios. An important issue is related to satellites with ultra-high or low elevation angles and satellites near the building boundary that are very likely to be misclassified. By solving this problem, the SVM classification shows the potential of about 90% classification accuracy for various urban cases. With the help of these approaches, the shadow matching has a mean error of 10.27 m with 1.44 m in the cross-street direction; these performances are suitable for urban positioning. | U74: eng | V74: drupal | W74: 169 | X74: 1 | Y74: yes | Z74: missing_doi | AB74: legacy_drupal_historical
A75: drupal-159 | B75: 2020 | D75: PANG-NAV: a tool for processing GNSS measurements in SPP, including RAIM functionality | E75: Antonio Angrisano; Salvatore Gaglione; N. Crocetto; Mario Vultaggio | F75: Salvatore Gaglione | G75: Journal Article | H75: GPS Solutions | L75: 24 | O75: 10.1007/s10291-019-0935-y | P75: 10.1007/s10291-019-0935-y | Q75: 10805370 | S75: https://www.scopus.com/inward/record.uri?eid=2-s2.0-85075862495&doi=10.1007%2fs10291-019-0935-y&partnerID=40&md5=5384d59813e59778298757bc15fbfe3b | U75: eng | V75: drupal | W75: 159 | X75: 1 | Y75: yes | AB75: legacy_drupal_historical
A76: drupal-170 | B76: 2020 | D76: Performance assessment of PPP surveys with open source software using the GNSS GPS-GLONASS-Galileo constellations | E76: Antonio Angrisano; G. Dardanelli; Anna Innac; A. Pisciotta; C. Pipitone; Salvatore Gaglione | F76: Salvatore Gaglione | G76: Journal Article | H76: Applied Sciences (Switzerland) | L76: 10 | O76: 10.3390/APP10165420 | P76: 10.3390/APP10165420 | Q76: 20763417 | S76: https://www.scopus.com/inward/record.uri?eid=2-s2.0-85089897851&doi=10.3390%2fAPP10165420&partnerID=40&md5=840e9e4b552a1db3893cbd9690964200 | U76: eng | V76: drupal | W76: 170 | X76: 1 | Y76: yes | AB76: legacy_drupal_historical
A77: drupal-222 | B77: 2020 | D77: Sea state monitoring based on ship motion measurements onboard an icebreaker in the Antarctic waters | E77: Silvia Pennino; Antonio Angrisano; Salvatore Gaglione; Anna Innac; Vincenzo Piscopo; Antonio Scamardella | F77: Silvia Pennino; Salvatore Gaglione; Vincenzo Piscopo; Antonio Scamardella | G77: Conference Paper | H77: MetroSea 2020 - TC19 International Workshop on Metrology for the Sea | S77: https://www.scopus.com/inward/record.uri?eid=2-s2.0-85123284262&partnerID=40&md5=3dfc9622ecf64d700fc7bad350f9b1d1 | U77: eng | V77: drupal | W77: 222 | X77: 1 | Y77: yes | Z77: missing_doi | AB77: legacy_drupal_historical
A78: drupal-200 | B78: 2020 | D78: THE FUSION of EXTERNAL and INTERNAL 3D PHOTOGRAMMETRIC MODELS AS A TOOL to INVESTIGATE the ANCIENT HUMAN/CAVE INTERACTION: The la SASSA CASE STUDY | E78: L. Alessandri; Valerio Baiocchi; Silvio Del Pizzo; Fabiana Di Ciaccio; Matteo Onori; M.F. Rolfo; Salvatore Troisi | F78: Silvio Del Pizzo; Salvatore Troisi | G78: Conference Paper | H78: International Archives of the Photogrammetry, Remote Sensing and Spatial Information Sciences - ISPRS Archives | O78: 10.5194/isprs-archives-XLIII-B2-2020-1443-2020 | P78: 10.5194/isprs-archives-XLIII-B2-2020-1443-2020 | S78: https://www.scopus.com/inward/record.uri?eid=2-s2.0-85091071189&doi=10.5194%2fisprs-archives-XLIII-B2-2020-1443-2020&partnerID=40&md5=e421ade7c6546555e9b8d1fd5d8838c9 | U78: eng | V78: drupal | W78: 200 | X78: 1 | Y78: yes | AB78: legacy_drupal_historical
A79: drupal-199 | B79: 2020 | D79: Use of the sensors of a latest generation mobile phone for the three-dimensional reconstruction of an archaeological monument: The survey of the Intihuatana stone in Machu Picchu (Peru') | E79: Valerio Baiocchi; Silvio Del Pizzo; Giovanni Pugliano; Matteo Onori; Umberto Robustelli; Salvatore Troisi; Felicia Vatore; F.J. León Trujillo | F79: Silvio Del Pizzo; Salvatore Troisi | G79: Conference Paper | H79: IOP Conference Series: Materials Science and Engineering | O79: 10.1088/1757-899X/949/1/012106 | P79: 10.1088/1757-899X/949/1/012106 | S79: https://www.scopus.com/inward/record.uri?eid=2-s2.0-85096880615&doi=10.1088%2f1757-899X%2f949%2f1%2f012106&partnerID=40&md5=a6379a25e3e08aabb241ca4063a4af96 | U79: eng | V79: drupal | W79: 199 | X79: 1 | Y79: yes | AB79: legacy_drupal_historical
A80: drupal-154 | B80: 2019 | D80: Fuzzy logic applied to GNSS | E80: Salvatore Gaglione; Antonio Angrisano; Anna Innac; Silvio Del Pizzo; Antonio Maratea | F80: Salvatore Gaglione; Silvio Del Pizzo | G80: Journal Article | H80: Measurement: Journal of the International Measurement Confederation | L80: 136 | N80: 314-322 | O80: 10.1016/j.measurement.2018.12.103 | P80: 10.1016/j.measurement.2018.12.103 | S80: https://www.scopus.com/inward/record.uri?eid=2-s2.0-85059515503&doi=10.1016%2fj.measurement.2018.12.103&partnerID=40&md5=c03a37912a86da8003de11f16bf3086d | T80: Limiting the weight of bad signals can recover the accuracy of the GNSS solution in signal-degraded scenarios, where multipath reflections and obstructions can easily generate multiple blunders. The fuzzy integration of the available information related to the quality of the received signals is exploited in this paper to derive an effective weighting schema in a Weighted Least Square estimation process. To validate the proposed schema, its performance in the position domain is compared to the most common weighting strategies proposed in the literature, based on GPS data collected through two different High Sensitivity GNSS receivers placed in urban canyons and processed in Single Point Positioning using pseudorange measurements. © 2019 Elsevier Ltd | U80: eng | V80: drupal | W80: 154 | X80: 1 | Y80: yes | AB80: legacy_drupal_historical
A81: drupal-153 | B81: 2019 | D81: Machine Learning application to context recognition of a smartphone in Pedestrian Navigation | E81: Francesco Giordano | G81: Thesis | U81: eng | V81: drupal | W81: 153 | X81: 1 | Y81: yes | Z81: missing_doi | AB81: legacy_drupal_historical
A82: drupal-156 | B82: 2019 | D82: Mitigation of leverage observation effects in GNSS robust positioning | E82: Antonio Angrisano; Salvatore Gaglione | F82: Salvatore Gaglione | G82: Conference Paper | H82: 2018 IEEE International Workshop on Metrology for the Sea; Learning to Measure Sea Health Parameters, MetroSea 2018 - Proceedings | J82: Institute of Electrical and Electronics Engineers Inc. | O82: 10.1109/MetroSea.2018.8657870 | P82: 10.1109/MetroSea.2018.8657870 | S82: https://www.scopus.com/inward/record.uri?eid=2-s2.0-85063866479&doi=10.1109%2fMetroSea.2018.8657870&partnerID=40&md5=05cadc7af731b0d1dffe0c904d6ac49c | T82: Nowadays GNSSs are the most commonly used systems for localization; they are able to provide user absolute position with metric accuracy in benign environment, i.e. in scenarios without significant obstacles surrounding the user. On the other hand, in harsh scenarios GNSS performance are degraded, owing to the shortage of available measurements and/or to the presence of blunders among them. The blunder issue is usually addressed through RAIM techniques or robust estimation; the latter approach demonstrates often better performance, but suffers anyway the cases of multiple blunders and low redundancy. M-estimators, a particular class of robust estimators, are based on the minimization of functions of least squares residuals. A possible way to strengthen a M-estimator is to take into account for leverage observations, defined as measurements with high potential to affect estimation results. In this work, the Huber M-estimator is adapted to include information about leverage observations and is used to process GPS measurements, collected in harsh environment. The obtained results are very promising, with position errors reduction even beyond 50% with respect to classical Huber method. © 2018 IEEE. | U82: eng | V82: drupal | W82: 156 | X82: 1 | Y82: yes | AB82: legacy_drupal_historical
A83: drupal-155 | B83: 2019 | D83: Multi-GNSS single frequency precise point positioning | E83: Anna Innac; Salvatore Gaglione; Antonio Angrisano | F83: Salvatore Gaglione | G83: Conference Paper | H83: 2018 IEEE International Workshop on Metrology for the Sea; Learning to Measure Sea Health Parameters, MetroSea 2018 - Proceedings | J83: Institute of Electrical and Electronics Engineers Inc. | O83: 10.1109/MetroSea.2018.8657857 | P83: 10.1109/MetroSea.2018.8657857 | S83: https://www.scopus.com/inward/record.uri?eid=2-s2.0-85063905389&doi=10.1109%2fMetroSea.2018.8657857&partnerID=40&md5=fdadaaf98244b0abb0fb6dd39560b864 | T83: Single Frequency-Precise Point Positioning (SF-PPP) processing strategy is a hot topic in GNSS context, owing to the advantages of a stand-alone, accurate and cost efficiency positioning. However, the existing SF-PPP methods can be hardly implemented for high-precision applications due to the large error sources that affect accuracy and converge time of PPP solution. For this aim, the paper proposes a SF-PPP approach based on the processing of code and carrier phase measurements from multi-GNSS constellation. The algorithm is tested using a static data collection carried out in an open-sky scenario. Results show a decimeter level accuracy on horizontal and vertical components of the position. © 2018 IEEE. | U83: eng | V83: drupal | W83: 155 | X83: 1 | Y83: yes | AB83: legacy_drupal_historical
A84: drupal-208 | B84: 2019 | D84: Multiscale reconstruction of natural and archaeological underwater landscape by optical and acoustic sensors | E84: Gaia Mattei; Salvatore Troisi; Pietro PC Aucelli; Gerardo Pappone; F. Peluso; M. Stefanile | F84: Salvatore Troisi | G84: Conference Paper | H84: 2018 IEEE International Workshop on Metrology for the Sea; Learning to Measure Sea Health Parameters, MetroSea 2018 - Proceedings | O84: 10.1109/MetroSea.2018.8657872 | P84: 10.1109/MetroSea.2018.8657872 | S84: https://www.scopus.com/inward/record.uri?eid=2-s2.0-85062507512&doi=10.1109%2fMetroSea.2018.8657872&partnerID=40&md5=f08590876fd52ce78acbef63d673f66a | U84: eng | V84: drupal | W84: 208 | X84: 1 | Y84: yes | Z84: ambiguous_author:Aucelli, P.P.C. | AB84: legacy_drupal_historical
A85: drupal-206 | B85: 2019 | D85: Optimization of the maritime signaling in the Venetian Lagoon | E85: Fabiana Di Ciaccio; P. Menegazzo; Salvatore Troisi | F85: Salvatore Troisi | G85: Conference Paper | H85: 2018 IEEE International Workshop on Metrology for the Sea; Learning to Measure Sea Health Parameters, MetroSea 2018 - Proceedings | O85: 10.1109/MetroSea.2018.8657844 | P85: 10.1109/MetroSea.2018.8657844 | S85: https://www.scopus.com/inward/record.uri?eid=2-s2.0-85063895417&doi=10.1109%2fMetroSea.2018.8657844&partnerID=40&md5=e8b850e98d7fec382c94d7fd1d19d08c | U85: eng | V85: drupal | W85: 206 | X85: 1 | Y85: yes | AB85: legacy_drupal_historical
A86: drupal-207 | B86: 2019 | D86: Optimization of the maritime signaling system in the lagoon of venice | E86: Fabiana Di Ciaccio; P. Menegazzo; Salvatore Troisi | F86: Salvatore Troisi | G86: Journal Article | H86: Sensors (Switzerland) | L86: 19 | O86: 10.3390/s19051216 | P86: 10.3390/s19051216 | S86: https://www.scopus.com/inward/record.uri?eid=2-s2.0-85062827774&doi=10.3390%2fs19051216&partnerID=40&md5=cd4fcf134389b327a73689ca1733f7ba | U86: eng | V86: drupal | W86: 207 | X86: 1 | Y86: yes | AB86: legacy_drupal_historical
A87: drupal-157 | B87: 2019 | D87: Pedestrian localization with PDR supplemented by GNSS | E87: Antonio Angrisano; Mario Vultaggio; Salvatore Gaglione; N. Crocetto | F87: Salvatore Gaglione | G87: Conference Paper | H87: European Navigation Conference, ENC 2019 | O87: 10.1109/EURONAV.2019.8714150 | P87: 10.1109/EURONAV.2019.8714150 | R87: 9781538694732 | S87: https://www.scopus.com/inward/record.uri?eid=2-s2.0-85067107796&doi=10.1109%2fEURONAV.2019.8714150&partnerID=40&md5=a7efc198b4f6ca91b8bcdfb0afd7fe5f | U87: eng | V87: drupal | W87: 157 | X87: 1 | Y87: yes | AB87: legacy_drupal_historical
A88: drupal-168 | B88: 2019 | C88: 2019 | D88: Performance comparison among multi-GNSS single frequency precise point positioning techniques | E88: Anna Innac; Antonio Angrisano; Salvatore Gaglione; Mario Vultaggio; N. Crocetto | F88: Salvatore Gaglione | G88: Journal Article | H88: Kartografija i Geoinformacije | L88: 18 | M88: 32 | N88: 80 - 99 | R88: 1333896X (ISSN) | S88: https://www.scopus.com/inward/record.uri?eid=2-s2.0-85084345198&doi=10.32909%2fkg.18.32.6&partnerID=40&md5=b97ced4c8edcbfed63867b718ed8a6e8 | U88: eng | V88: drupal | W88: 168 | X88: 1 | Y88: yes | Z88: missing_doi | AB88: legacy_drupal_historical
A89: drupal-209 | B89: 2019 | D89: PHOTOGRAMMETRIC SURVEY with FISHEYE LENS for the CHARACTERIZATION of the la SASSA CAVE | E89: L. Alessandri; Valerio Baiocchi; Silvio Del Pizzo; M.F. Rolfo; Salvatore Troisi | F89: Silvio Del Pizzo; Salvatore Troisi | G89: Conference Paper | H89: ISPRS Annals of the Photogrammetry, Remote Sensing and Spatial Information Sciences | O89: 10.5194/isprs-archives-XLII-2-W9-25-2019 | P89: 10.5194/isprs-archives-XLII-2-W9-25-2019 | S89: https://www.scopus.com/inward/record.uri?eid=2-s2.0-85065400824&doi=10.5194%2fisprs-archives-XLII-2-W9-25-2019&partnerID=40&md5=335e04bffaebad667be2a67ecb809351 | U89: eng | V89: drupal | W89: 209 | X89: 1 | Y89: yes | AB89: legacy_drupal_historical
A90: drupal-158 | B90: 2019 | D90: Robust Kalman Filter applied to GNSS positioning in harsh environment | E90: Salvatore Gaglione; Antonio Angrisano; N. Crocetto | F90: Salvatore Gaglione | G90: Conference Paper | H90: European Navigation Conference, ENC 2019 | O90: 10.1109/EURONAV.2019.8714132 | P90: 10.1109/EURONAV.2019.8714132 | R90: 9781538694732 | S90: https://www.scopus.com/inward/record.uri?eid=2-s2.0-85067099572&doi=10.1109%2fEURONAV.2019.8714132&partnerID=40&md5=c0cb8dcff95f925439f0bd622391205c | U90: eng | V90: drupal | W90: 158 | X90: 1 | Y90: yes | AB90: legacy_drupal_historical
A91: drupal-205 | B91: 2019 | D91: Three-dimensional survey of guattari cave with traditional and mobile phone cameras | E91: L. Alessandri; Valerio Baiocchi; Silvio Del Pizzo; Fabiana Di Ciaccio; Matteo Onori; M.F. Rolfo; Salvatore Troisi | F91: Silvio Del Pizzo; Salvatore Troisi | G91: Conference Paper | H91: ISPRS Annals of the Photogrammetry, Remote Sensing and Spatial Information Sciences | O91: 10.5194/isprs-Archives-XLII-2-W11-37-2019 | P91: 10.5194/isprs-Archives-XLII-2-W11-37-2019 | S91: https://www.scopus.com/inward/record.uri?eid=2-s2.0-85065652753&doi=10.5194%2fisprs-Archives-XLII-2-W11-37-2019&partnerID=40&md5=f68c468a1ec426380e016417e2f3a0a0 | U91: eng | V91: drupal | W91: 205 | X91: 1 | Y91: yes | AB91: legacy_drupal_historical
A92: drupal-151 | B92: 2018 | D92: A comparison between resistant GNSS positioning techniques in harsh environment | E92: Antonio Angrisano; Salvatore Gaglione; Antonio Maratea | F92: Salvatore Gaglione | G92: Conference Paper | H92: 2018 European Navigation Conference, ENC 2018 | O92: 10.1109/EURONAV.2018.8433232 | P92: 10.1109/EURONAV.2018.8433232 | S92: https://www.scopus.com/inward/record.uri?eid=2-s2.0-85052524533&doi=10.1109%2fEURONAV.2018.8433232&partnerID=40&md5=5929842ba87603741907b4d92d16cd2d | U92: eng | V92: drupal | W92: 151 | X92: 1 | Y92: yes | AB92: legacy_drupal_historical
A93: drupal-152 | B93: 2018 | D93: A proposed fault detection and exclusion method applied to multi-GNSS single-frequency PPP | E93: Anna Innac; Salvatore Gaglione; Salvatore Troisi; Antonio Angrisano | F93: Salvatore Gaglione; Salvatore Troisi | G93: Conference Paper | H93: 2018 European Navigation Conference, ENC 2018 | O93: 10.1109/EURONAV.2018.8433231 | P93: 10.1109/EURONAV.2018.8433231 | S93: https://www.scopus.com/inward/record.uri?eid=2-s2.0-85052516238&doi=10.1109%2fEURONAV.2018.8433231&partnerID=40&md5=7c480a8e72ecb3ea89f5783aa0fd83be | U93: eng | V93: drupal | W93: 152 | X93: 1 | Y93: yes | AB93: legacy_drupal_historical
A94: drupal-140 | B94: 2018 | D94: A resampling strategy based on bootstrap to reduce the effect of large blunders in GPS absolute positioning | E94: Antonio Angrisano; Antonio Maratea; Salvatore Gaglione | F94: Salvatore Gaglione | G94: Journal Article | H94: Journal of Geodesy | N94: 1-12 | O94: 10.1007/s00190-017-1046-6 | P94: 10.1007/s00190-017-1046-6 | S94: https://www.scopus.com/inward/record.uri?eid=2-s2.0-85022001142&doi=10.1007%2fs00190-017-1046-6&partnerID=40&md5=9893353c2c5296cc57f808acf611717a | T94: In the absence of obstacles, a GPS device is generally able to provide continuous and accurate estimates of position, while in urban scenarios buildings can generate multipath and echo-only phenomena that severely affect the continuity and the accuracy of the provided estimates. Receiver autonomous integrity monitoring (RAIM) techniques are able to reduce the negative consequences of large blunders in urban scenarios, but require both a good redundancy and a low contamination to be effective. In this paper a resampling strategy based on bootstrap is proposed as an alternative to RAIM, in order to estimate accurately position in case of low redundancy and multiple blunders: starting with the pseudorange measurement model, at each epoch the available measurements are bootstrapped—that is random sampled with replacement—and the generated a posteriori empirical distribution is exploited to derive the final position. Compared to standard bootstrap, in this paper the sampling probabilities are not uniform, but vary according to an indicator of the measurement quality. The proposed method has been compared with two different RAIM techniques on a data set collected in critical conditions, resulting in a clear improvement on all considered figures of merit. | U94: eng | V94: drupal | W94: 140 | X94: 1 | Y94: yes | AB94: legacy_drupal_historical
A95: drupal-147 | B95: 2018 | D95: A Vision-based navigation system for landing procedure | E95: Silvio Del Pizzo; Umberto Papa; Salvatore Gaglione; Salvatore Troisi; Giuseppe Del Core | F95: Silvio Del Pizzo; Salvatore Gaglione; Salvatore Troisi | G95: Journal Article | H95: ACTA IMEKO | U95: eng | V95: drupal | W95: 147 | X95: 1 | Y95: yes | Z95: missing_doi | AB95: legacy_drupal_historical
A96: drupal-146 | B96: 2018 | D96: Non parametric and robust statistics for indoor distance estimation through BLE | E96: Salvatore Gaglione; Antonio Maratea; Giuseppe Salvi; Antonio Angrisano; Alessandro Nunziata | F96: Salvatore Gaglione | G96: Conference Paper | H96: IEEE EE 2018 proceedings | U96: eng | V96: drupal | W96: 146 | X96: 1 | Y96: yes | Z96: missing_doi | AB96: legacy_drupal_historical
A97: drupal-148 | B97: 2018 | D97: Position Accuracy Analysis of a Robust Vision-Based Navigation System | E97: Salvatore Gaglione; Silvio Del Pizzo; Salvatore Troisi; Antonio Angrisano | F97: Salvatore Gaglione; Silvio Del Pizzo; Salvatore Troisi | G97: Conference Paper | H97: Proceedings of ISPRS Technical Commission II "Towards Photogrammetry 2020" | U97: eng | V97: drupal | W97: 148 | X97: 1 | Y97: yes | Z97: missing_doi | AB97: legacy_drupal_historical
A98: drupal-212 | B98: 2018 | D98: Position accuracy analysis of a robust vision-based navigation system | E98: Salvatore Gaglione; Silvio Del Pizzo; Salvatore Troisi; Antonio Angrisano | F98: Salvatore Gaglione; Silvio Del Pizzo; Salvatore Troisi | G98: Conference Paper | H98: International Archives of the Photogrammetry, Remote Sensing and Spatial Information Sciences - ISPRS Archives | O98: 10.5194/isprs-archives-XLII-2-355-2018 | P98: 10.5194/isprs-archives-XLII-2-355-2018 | S98: https://www.scopus.com/inward/record.uri?eid=2-s2.0-85048361729&doi=10.5194%2fisprs-archives-XLII-2-355-2018&partnerID=40&md5=fe395813d5f316330f8bd6b71295b535 | U98: eng | V98: drupal | W98: 212 | X98: 1 | Y98: yes | AB98: legacy_drupal_historical
A99: drupal-145 | B99: 2018 | D99: Reliable vessel attitude estimation by wide angle camera | E99: Silvio Del Pizzo; Salvatore Gaglione; Antonio Angrisano; Giuseppe Salvi; Salvatore Troisi | F99: Silvio Del Pizzo; Salvatore Gaglione; Salvatore Troisi | G99: Journal Article | H99: Measurement: Journal of the International Measurement Confederation | L99: 127 | N99: 314-324 | O99: 10.1016/j.measurement.2018.05.104 | P99: 10.1016/j.measurement.2018.05.104 | S99: https://www.scopus.com/inward/record.uri?eid=2-s2.0-85048158987&doi=10.1016%2fj.measurement.2018.05.104&partnerID=40&md5=37a32db506f1bd53d241509ca2094f96 | U99: eng | V99: drupal | W99: 145 | X99: 1 | Y99: yes | AB99: legacy_drupal_historical
A100: drupal-211 | B100: 2018 | D100: Reliable vessel attitude estimation by wide angle camera | E100: Silvio Del Pizzo; Salvatore Gaglione; Antonio Angrisano; Giuseppe Salvi; Salvatore Troisi | F100: Silvio Del Pizzo; Salvatore Gaglione; Salvatore Troisi | G100: Journal Article | H100: Measurement: Journal of the International Measurement Confederation | L100: 127 | N100: 314-324 | O100: 10.1016/j.measurement.2018.05.104 | P100: 10.1016/j.measurement.2018.05.104 | S100: https://www.scopus.com/inward/record.uri?eid=2-s2.0-85048158987&doi=10.1016%2fj.measurement.2018.05.104&partnerID=40&md5=37a32db506f1bd53d241509ca2094f96 | U100: eng | V100: drupal | W100: 211 | X100: 1 | Y100: yes | AB100: legacy_drupal_historical
...

Sheet Scopus review
A1: publication_id | B1: year | C1: date | D1: title | E1: authors | F1: pang_faculty_authors | G1: document_type | H1: source_title | I1: volume | J1: issue | K1: pages | L1: doi | M1: scopus_eid | N1: scopus_url | O1: source_url | P1: verification_status | Q1: verification_evidence | R1: include_in_master | S1: notes
A2: scopus-10-1109-taes-2025-3619912 | B2: 2026 | D2: A Split Pulse Fusion Method for Radar Reconnaissance | E2: Ronghua Guo; Yang-Yang Dong; Dan Bao; Chunxi Dong; Sergio Vitale; Giampaolo Ferraioli; Vito Pascazio; Wenbo Li; Zhiyuan Li | F2: Giampaolo Ferraioli | G2: Journal Article | H2: IEEE Transactions on Aerospace and Electronic Systems | I2: 62 | K2: 217-233 | L2: 10.1109/TAES.2025.3619912 | O2: https://www.sciencedirect.com/author/7003486376/vito-pascazio | P2: verified_scopus | Q2: ScienceDirect author page labels the publication “Scopus Article”. | R2: yes
A3: scopus-10-3390-geomatics6010004 | B3: 2026 | C3: 2026-01-10 | D3: Evaluating Neural Radiance Fields for Image-Based 3D Reconstruction: A Comparative Study with SfM-MVS | E3: Alessia Giaquinto; Giampaolo Ferraioli; Silvio Del Pizzo | F3: Giampaolo Ferraioli; Silvio Del Pizzo | G3: Journal Article | H3: Geomatics | I3: 6 | J3: 1 | K3: 4 | L3: 10.3390/geomatics6010004 | O3: https://www.mdpi.com/2673-7418/6/1/4 | P3: pending_scopus | Q3: Publisher record confirmed; direct Scopus record/EID not yet retrieved. | R3: no
A4: scopus-10-3390-automation7020036 | B4: 2026 | C4: 2026-02-25 | D4: Intelligent Tomato Leaf Disease Detection and Automated Spray Prescription Using YOLOv9: A Smart Agriculture Approach | E4: Shahab Ul Islam; Giampaolo Ferraioli; Ghassan Husnain; Abdul Waheed; Vito Pascazio | F4: Giampaolo Ferraioli | G4: Journal Article | H4: Automation | I4: 7 | J4: 2 | K4: 36 | L4: 10.3390/automation7020036 | O4: https://www.sciencedirect.com/author/7003486376/vito-pascazio | P4: verified_scopus | Q4: ScienceDirect author page lists the Automation 2026 record as “Scopus Article”. | R4: yes
A5: scopus-10-3390-engproc2026126010 | B5: 2026 | C5: 2026-02-11 | D5: On the Context-Aware GNSS Navigation: Test of a k-Nearest Neighbors Classifier in Different Environments | E5: Giovanni Cappello; Antonio Angrisano; Ciro Gioia; Antonio Maratea; Salvatore Gaglione | F5: Salvatore Gaglione | G5: Conference Paper | H5: Engineering Proceedings | I5: 126 | J5: 1 | K5: 10 | L5: 10.3390/engproc2026126010 | O5: https://www.mdpi.com/2673-4591/126/1/10 | P5: pending_scopus | Q5: Publisher record confirmed; direct Scopus record/EID not yet retrieved. | R5: no
A6: scopus-10-1016-j-oceaneng-2025-123471 | B6: 2026 | C6: 2026-01-15 | D6: Sea state reconstruction based on the Spearman rank correlation using full-scale data from a containership | E6: Silvia Ascione; Ulrik D. Nielsen; Vincenzo Piscopo; Gaute Storhaug | F6: Vincenzo Piscopo | G6: Journal Article | H6: Ocean Engineering | I6: 343 | J6: Part 4 | K6: 123471 | L6: 10.1016/j.oceaneng.2025.123471 | O6: https://www.sciencedirect.com/author/57224792997/ulrik-dam-nielsen | P6: verified_scopus | Q6: ScienceDirect author page provides “View details in Scopus” for this article. | R6: yes
A7: scopus-10-1109-lgrs-2026-3659009 | B7: 2026 | D7: Sentinel-1 Ground Truth Dataset for Coastline Extraction | E7: Gianpaolo Passarello; Sergio Vitale; Giampaolo Ferraioli; Vito Pascazio | F7: Giampaolo Ferraioli | G7: Journal Article | H7: IEEE Geoscience and Remote Sensing Letters | I7: 23 | L7: 10.1109/LGRS.2026.3659009 | O7: https://www.sciencedirect.com/author/7003486376/vito-pascazio | P7: verified_scopus | Q7: ScienceDirect author page labels the publication “Scopus Article”. | R7: yes
A8: scopus-10-1109-lgrs-2025-3555441 | B8: 2025 | D8: A Deep Learning Solution for Phase Screen Estimation in SAR Tomography | E8: Hossein Aghababaei; Giampaolo Ferraioli; Sergio Vitale; Alfred Stein | F8: Giampaolo Ferraioli | G8: Journal Article | H8: IEEE Geoscience and Remote Sensing Letters | I8: 22 | K8: 4007605 | L8: 10.1109/LGRS.2025.3555441 | O8: https://research.utwente.nl/en/publications/a-deep-learning-solution-for-phase-screen-estimation-in-sar-tomog/ | P8: verified_scopus_indirect | Q8: University of Twente research portal exposes Scopus citation data for the publication. | R8: yes
A9: scopus-10-1109-metroaerospace64938-2025-11114485 | B9: 2025 | D9: A Micro Radar-Based Low-Cost Solution for Positioning and Detection, and Avoidance System | E9: Gennaro Ariante; Lucie Rocquelain; Salvatore Gaglione; Silvio Del Pizzo; Giuseppe Del Core | F9: Salvatore Gaglione; Silvio Del Pizzo | G9: Conference Paper | H9: 2025 IEEE International Workshop on Metrology for AeroSpace, MetroAeroSpace 2025 - Proceedings | L9: 10.1109/MetroAeroSpace64938.2025.11114485 | M9: 2-s2.0-105015377060 | N9: https://www.scopus.com/inward/record.uri?eid=2-s2.0-105015377060&doi=10.1109%2fMetroAeroSpace64938.2025.11114485&partnerID=40&md5=03287e527efef9f4adf9d23e9c84507f | O9: https://www.scopus.com/inward/record.uri?eid=2-s2.0-105015377060&doi=10.1109%2fMetroAeroSpace64938.2025.11114485&partnerID=40&md5=03287e527efef9f4adf9d23e9c84507f | P9: verified_scopus | Q9: Direct Scopus inward URL/EID stored in the legacy Drupal record. | R9: yes | S9: Recovered from Drupal 2025; treated as Scopus source for the new master.
A10: scopus-10-1016-j-oceaneng-2025-121579 | B10: 2025 | D10: A numerical model of ship manoeuvring for the KVLCC2 hull, in regular and long-crested irregular waves | E10: Maria Acanfora; Marco Altosole; Silvia Pennino | F10: Silvia Pennino | G10: Journal Article | H10: Ocean Engineering | I10: 333 | K10: 121579 | L10: 10.1016/j.oceaneng.2025.121579 | O10: https://ouci.dntb.gov.ua/works/9Gmm8Yyx/ | P10: verified_scopus | Q10: OUCI record explicitly marks the article as indexed in Scopus. | R10: yes
A11: scopus-10-1109-metrosea66681-2025-11245754 | B11: 2025 | D11: Advancing Offshore Renewable Energy in the Mediterranean Sea: Digital-Med, a Project for Integrating Resource Assessment and Decision Support | E11: Silvio Del Pizzo; Salvatore Gaglione; Pier Paolo Amoroso; Pasquale Contestabile; Yuri Cotroneo; Francesco Giuseppe Figliomeni; Diego Vicinanza; Giorgio Budillon | F11: Silvio Del Pizzo; Salvatore Gaglione | G11: Conference Paper | H11: 2025 IEEE International Workshop on Metrology for the Sea; Learning to Measure Sea Health Parameters, MetroSea 2025 - Proceedings | L11: 10.1109/MetroSea66681.2025.11245754 | M11: 2-s2.0-105029542122 | N11: https://www.scopus.com/inward/record.uri?eid=2-s2.0-105029542122&doi=10.1109%2fMetroSea66681.2025.11245754&partnerID=40&md5=deea9b4f945a9ec20267bce45c30d977 | O11: https://www.scopus.com/inward/record.uri?eid=2-s2.0-105029542122&doi=10.1109%2fMetroSea66681.2025.11245754&partnerID=40&md5=deea9b4f945a9ec20267bce45c30d977 | P11: verified_scopus | Q11: Direct Scopus inward URL/EID stored in the legacy Drupal record. | R11: yes | S11: Recovered from Drupal 2025; treated as Scopus source for the new master.
A12: scopus-10-1109-igarss55030-2025-11243038 | B12: 2025 | C12: 2025-08 | D12: An Open-Access Cross-Modal Forest Benchmark Training Dataset With Sentinel-1 and Lidar data | E12: Hossein Aghababaei; Giampaolo Ferraioli; Gilda Schirinzi; Erkki Tomppo; Jaan Praks | F12: Giampaolo Ferraioli | G12: Conference Paper | H12: IGARSS 2025 - 2025 IEEE International Geoscience and Remote Sensing Symposium | K12: 3588-3591 | L12: 10.1109/IGARSS55030.2025.11243038 | M12: 2-s2.0-105034117757 | N12: https://www.scopus.com/pages/publications/105034117757 | O12: https://research.aalto.fi/en/publications/an-open-access-cross-modal-forest-benchmark-training-dataset-with/ | P12: verified_scopus | Q12: Aalto research portal exposes direct Scopus URL and AN=SCOPUS:105034117757. | R12: yes
A13: scopus-10-1016-j-oceaneng-2025-122258 | B13: 2025 | C13: 2025-11-30 | D13: Assessment of bimodal sea states by the wave buoy analogy method | E13: Vincenzo Piscopo; Silvia Ascione; Antonio Scamardella | F13: Vincenzo Piscopo; Antonio Scamardella | G13: Journal Article | H13: Ocean Engineering | I13: 340 | J13: Part 1 | K13: 122258 | L13: 10.1016/j.oceaneng.2025.122258 | O13: https://www.sciencedirect.com/author/6507257720/v-piscopo | P13: verified_scopus | Q13: ScienceDirect author page provides “View details in Scopus”; OUCI independently labels the record Scopus. | R13: yes
A14: scopus-10-1038-s41598-025-00653-8 | B14: 2025 | C14: 2025-05-12 | D14: Augustus’ solar meridian functioning and the birth of the western leap year | E14: V. Baiocchi; M. Baumgartner; M. Barbarella; M. T. D’Alessio; Silvio Del Pizzo; F. Giannone; F. Radicioni; A. Stoppini; G. Tosi; Salvatore Troisi; L. Alessandri | F14: Silvio Del Pizzo; Salvatore Troisi | G14: Journal Article | H14: Scientific Reports | I14: 15 | K14: 16463 | L14: 10.1038/s41598-025-00653-8 | O14: https://research.rug.nl/en/publications/augustus-solar-meridian-functioning-and-the-birth-of-the-western-/ | P14: verified_scopus_indirect | Q14: University of Groningen research portal reports Scopus citation data for this record. | R14: yes
A15: scopus-10-3233-pmst250035 | B15: 2025 | C15: 2025-08-12 | D15: Development and Application of a Numerical Model for Ship Manoeuvring in Regular and Irregular Waves | E15: Maria Acanfora; Silvia Pennino; Antonio Scamardella | F15: Silvia Pennino; Antonio Scamardella | G15: Conference Paper / Book Chapter | H15: Technology and Science for the Ships of the Future | L15: 10.3233/PMST250035 | O15: https://journals.sagepub.com/doi/10.3233/PMST250035 | P15: pending_scopus | Q15: Publisher record confirmed; direct Scopus record/EID not yet retrieved. | R15: no
A16: scopus-10-1109-lgrs-2025-3577907 | B16: 2025 | D16: Enhanced Deep Learning SAR Despeckling Networks Based on SAR Assessing Metrics | E16: Sergio Vitale; Giampaolo Ferraioli; Vito Pascazio; Luis Gomez Deniz | F16: Giampaolo Ferraioli | G16: Journal Article | H16: IEEE Geoscience and Remote Sensing Letters | I16: 22 | K16: 4009305 | L16: 10.1109/LGRS.2025.3577907 | O16: https://accedacris.ulpgc.es/handle/10553/141828 | P16: probable_scopus | Q16: Published in IEEE GRSL; public CRIS confirms metadata, but no direct Scopus EID was exposed in the retrieved record. | R16: no | S16: Keep pending until direct Scopus confirmation/EID is obtained.
A17: scopus-10-1109-lgrs-2025-3580932 | B17: 2025 | C17: 2025-07-17 | D17: Erratum to “A deep learning solution for phase screen estimation in SAR tomography” | E17: Hossein Aghababaei; Giampaolo Ferraioli; Sergio Vitale; Alfred Stein | F17: Giampaolo Ferraioli | G17: Erratum | H17: IEEE Geoscience and Remote Sensing Letters | I17: 22 | K17: 1-1 | L17: 10.1109/LGRS.2025.3580932 | O17: https://research.utwente.nl/en/publications/erratum-to-a-deep-learning-solution-for-phase-screen-estimation-i/ | P17: probable_scopus | Q17: Twente record links the parent publication to Scopus; direct Scopus identifier for the erratum was not exposed. | R17: no | S17: Pending direct Scopus confirmation.
A18: scopus-10-1109-mgrs-2025-3612752 | B18: 2025 | C18: 2025-12-17 | D18: IEEE Geoscience and Remote Sensing Society Awards Presented at the IEEE International Geoscience and Remote Sensing Symposium 2025 Awards Reception and Ceremony | E18: Francesca Bovolo; Jaya Sreevalsan-Nair; Antonio Plaza; Alberto Moreira; Giampaolo Ferraioli; Claudio Persello | F18: Giampaolo Ferraioli | G18: Conference Report | H18: IEEE Geoscience and Remote Sensing Magazine | I18: 13 | K18: 444-454 | L18: 10.1109/MGRS.2025.3612752 | O18: https://elib.dlr.de/222017/ | P18: verified_scopus | Q18: DLR publication record explicitly states “In SCOPUS: Ja”. | R18: yes | S18: Non-research conference report; retain with document_type so it can be filtered if desired.
A19: scopus-10-1109-mgrs-2025-3599367 | B19: 2025 | C19: 2025-12 | D19: IGARSS 2025 in Brisbane, Australia: Impressions of the First Days | E19: Alberto Moreira; Francesca Bovolo; Jaya Sreevalsan-Nair; Giampaolo Ferraioli | F19: Giampaolo Ferraioli | G19: Conference Report | H19: IEEE Geoscience and Remote Sensing Magazine | I19: 13 | J19: 4 | K19: 430-443 | L19: 10.1109/MGRS.2025.3599367 | O19: https://elib.dlr.de/218787/ | P19: verified_scopus | Q19: DLR publication record explicitly states “In SCOPUS: Ja”. | R19: yes | S19: Non-research conference report; retain with document_type so it can be filtered if desired.
A20: scopus-10-3233-pmst250112 | B20: 2025 | C20: 2025-08-12 | D20: Incidence of Rank Correlation Algorithm on the Assessment of Bimodal Sea State Conditions Based on Ship Motion Analysis | E20: Vincenzo Piscopo; Antonio Scamardella | F20: Vincenzo Piscopo; Antonio Scamardella | G20: Conference Paper / Book Chapter | H20: Technology and Science for the Ships of the Future | L20: 10.3233/PMST250112 | O20: https://journals.sagepub.com/doi/10.3233/PMST250112 | P20: pending_scopus | Q20: Publisher record confirmed; direct Scopus record/EID not yet retrieved. | R20: no
A21: scopus-10-33012-2025-19984 | B21: 2025 | D21: The G4 Solar Storm of May 2024: Impact on the GNSS carrier-phase measurements | E21: Giovanni Cappello; Ciro Gioia; Antonio Angrisano; Gabriele Portelli; Salvatore Gaglione | F21: Salvatore Gaglione | G21: Conference Paper | H21: Proceedings of the International Technical Meeting of The Institute of Navigation, ITM | L21: 10.33012/2025.19984 | M21: 2-s2.0-105001675036 | N21: https://www.scopus.com/inward/record.uri?eid=2-s2.0-105001675036&doi=10.33012%2f2025.19984&partnerID=40&md5=739f848160bb42247f9941f85f76ae90 | O21: https://www.scopus.com/inward/record.uri?eid=2-s2.0-105001675036&doi=10.33012%2f2025.19984&partnerID=40&md5=739f848160bb42247f9941f85f76ae90 | P21: verified_scopus | Q21: Direct Scopus inward URL/EID stored in the legacy Drupal record. | R21: yes | S21: Recovered from Drupal 2025; treated as Scopus source for the new master.
A22: scopus-10-1109-metroaerospace64938-2025-11114637 | B22: 2025 | D22: The Galileo-based UAV velocity: Doppler and Time-Differenced Carrier Phase | E22: Giovanni Cappello; Ciro Gioia; Andrea Piccolo; Antonio Angrisano; Salvatore Gaglione | F22: Salvatore Gaglione | G22: Conference Paper | H22: 2025 IEEE International Workshop on Metrology for AeroSpace, MetroAeroSpace 2025 - Proceedings | L22: 10.1109/MetroAeroSpace64938.2025.11114637 | M22: 2-s2.0-105015510478 | N22: https://www.scopus.com/inward/record.uri?eid=2-s2.0-105015510478&doi=10.1109%2fMetroAeroSpace64938.2025.11114637&partnerID=40&md5=7eb302fc7d501619ffc0077b7e307cfc | O22: https://www.scopus.com/inward/record.uri?eid=2-s2.0-105015510478&doi=10.1109%2fMetroAeroSpace64938.2025.11114637&partnerID=40&md5=7eb302fc7d501619ffc0077b7e307cfc | P22: verified_scopus | Q22: Direct Scopus inward URL/EID stored in the legacy Drupal record. | R22: yes | S22: Recovered from Drupal 2025; treated as Scopus source for the new master.
A23: scopus-10-33012-2025-19974 | B23: 2025 | D23: The synthetic meta-signal observations: a multipath resistance assessment | E23: Giovanni Cappello; Ciro Gioia; Antonio Angrisano; Salvatore Gaglione | F23: Salvatore Gaglione | G23: Conference Paper | H23: Proceedings of the International Technical Meeting of The Institute of Navigation, ITM | L23: 10.33012/2025.19974 | M23: 2-s2.0-105001668620 | N23: https://www.scopus.com/inward/record.uri?eid=2-s2.0-105001668620&doi=10.33012%2f2025.19974&partnerID=40&md5=e3784e375792ec1833f2de6d00e0ea7b | O23: https://www.scopus.com/inward/record.uri?eid=2-s2.0-105001668620&doi=10.33012%2f2025.19974&partnerID=40&md5=e3784e375792ec1833f2de6d00e0ea7b | P23: verified_scopus | Q23: Direct Scopus inward URL/EID stored in the legacy Drupal record. | R23: yes | S23: Recovered from Drupal 2025; treated as Scopus source for the new master.
A24: scopus-10-3390-agriengineering7040120 | B24: 2025 | C24: 2025-04 | D24: Tomato Leaf Detection, Segmentation, and Extraction in Real-Time Environment for Accurate Disease Detection | E24: Shahab Ul Islam; Giampaolo Ferraioli; Vito Pascazio | F24: Giampaolo Ferraioli | G24: Journal Article | H24: AgriEngineering | I24: 7 | J24: 4 | K24: 120 | L24: 10.3390/agriengineering7040120 | O24: https://ouci.dntb.gov.ua/en/works/l111xP2y/ | P24: verified_scopus | Q24: OUCI record explicitly marks the article as indexed in Scopus. | R24: yes
A25: scopus-10-3390-engproc2025088014 | B25: 2025 | D25: Toward Context-Aware GNSS Positioning: A Preliminary Analysis | E25: Giovanni Cappello; Antonio Maratea; Ciro Gioia; Antonio Angrisano; Silvio Del Pizzo; Salvatore Gaglione | F25: Silvio Del Pizzo; Salvatore Gaglione | G25: Journal Article | H25: Engineering Proceedings | I25: 88 | L25: 10.3390/engproc2025088014 | M25: 2-s2.0-105023666393 | N25: https://www.scopus.com/inward/record.uri?eid=2-s2.0-105023666393&doi=10.3390%2fengproc2025088014&partnerID=40&md5=062a75da7c74085f6b1f50a1bc441882 | O25: https://www.scopus.com/inward/record.uri?eid=2-s2.0-105023666393&doi=10.3390%2fengproc2025088014&partnerID=40&md5=062a75da7c74085f6b1f50a1bc441882 | P25: verified_scopus | Q25: Direct Scopus inward URL/EID stored in the legacy Drupal record. | R25: yes | S25: Recovered from Drupal 2025; treated as Scopus source for the new master.
A26: scopus-10-5194-isprs-archives-xlviii-2-w10-2025-207-2025 | B26: 2025 | C26: 2025-07-07 | D26: Underwater optical metrology for precision monitoring of marine habitats: the MANATEE project | E26: Erica Nocerino; Fabio Menna; Alessio Calantropio; Federico Pinna; Silvio Del Pizzo; Simone Farina; Alessia Giaquinto; Alessandro Lambertini; Massimiliano Menghini; Shahriar Mokhtari; Federica Ragazzola; Salvatore Troisi; Luca Vittuari | F26: Silvio Del Pizzo; Salvatore Troisi | G26: Conference Paper | H26: The International Archives of the Photogrammetry, Remote Sensing and Spatial Information Sciences | I26: XLVIII-2/W10-2025 | K26: 207-214 | L26: 10.5194/isprs-archives-XLVIII-2-W10-2025-207-2025 | O26: https://isprs-archives.copernicus.org/articles/XLVIII-2-W10-2025/207/2025/index.html | P26: pending_scopus | Q26: Bibliographic record confirmed by publisher; direct Scopus record/EID not yet retrieved. | R26: no
A27: scopus-10-5194-isprs-archives-xlviii-2-w10-2025-47-2025 | B27: 2025 | C27: 2025-07-07 | D27: Underwater synthetic image generation for multi-temporal monitoring of crustose coralline algae | E27: Alessio Calantropio; Alessia Giaquinto; Silvio Del Pizzo; Fabio Menna; Erica Nocerino | F27: Silvio Del Pizzo | G27: Conference Paper | H27: The International Archives of the Photogrammetry, Remote Sensing and Spatial Information Sciences | I27: XLVIII-2/W10-2025 | K27: 47-54 | L27: 10.5194/isprs-archives-XLVIII-2-W10-2025-47-2025 | O27: https://isprs-archives.copernicus.org/articles/XLVIII-2-W10-2025/47/2025/isprs-archives-XLVIII-2-W10-2025-47-2025.html | P27: pending_scopus | Q27: Bibliographic record confirmed by publisher; direct Scopus record/EID not yet retrieved. | R27: no

Sheet Faculty coverage
A1: Faculty | B1: Verified/Included | C1: Pending/Probable | D1: Total candidates
A2: Salvatore Gaglione | B2: =COUNTIFS('Scopus review'!$F:$F,"*"&A2&"*",'Scopus review'!$R:$R,"yes") | C2: =COUNTIFS('Scopus review'!$F:$F,"*"&A2&"*",'Scopus review'!$R:$R,"no") | D2: =B2+C2
A3: Salvatore Troisi | B3: =COUNTIFS('Scopus review'!$F:$F,"*"&A3&"*",'Scopus review'!$R:$R,"yes") | C3: =COUNTIFS('Scopus review'!$F:$F,"*"&A3&"*",'Scopus review'!$R:$R,"no") | D3: =B3+C3
A4: Silvio Del Pizzo | B4: =COUNTIFS('Scopus review'!$F:$F,"*"&A4&"*",'Scopus review'!$R:$R,"yes") | C4: =COUNTIFS('Scopus review'!$F:$F,"*"&A4&"*",'Scopus review'!$R:$R,"no") | D4: =B4+C4
A5: Giampaolo Ferraioli | B5: =COUNTIFS('Scopus review'!$F:$F,"*"&A5&"*",'Scopus review'!$R:$R,"yes") | C5: =COUNTIFS('Scopus review'!$F:$F,"*"&A5&"*",'Scopus review'!$R:$R,"no") | D5: =B5+C5
A6: Vincenzo Piscopo | B6: =COUNTIFS('Scopus review'!$F:$F,"*"&A6&"*",'Scopus review'!$R:$R,"yes") | C6: =COUNTIFS('Scopus review'!$F:$F,"*"&A6&"*",'Scopus review'!$R:$R,"no") | D6: =B6+C6
A7: Antonio Scamardella | B7: =COUNTIFS('Scopus review'!$F:$F,"*"&A7&"*",'Scopus review'!$R:$R,"yes") | C7: =COUNTIFS('Scopus review'!$F:$F,"*"&A7&"*",'Scopus review'!$R:$R,"no") | D7: =B7+C7
A8: Silvia Pennino | B8: =COUNTIFS('Scopus review'!$F:$F,"*"&A8&"*",'Scopus review'!$R:$R,"yes") | C8: =COUNTIFS('Scopus review'!$F:$F,"*"&A8&"*",'Scopus review'!$R:$R,"no") | D8: =B8+C8
